Workbook

Sheet Dashboard
A1: PAINEL DE CONTROLE — ALMOXARIFADO BOIBOM
A4: Clique em um botão para abrir a aba correspondente.
A6: 📦 ANALISAR ESTOQUE
A9: Ver o que precisa comprar agora, mínimo/máximo por item
A11: 🛒 ANALISAR COMPRAS
A14: Pedidos pendentes, solicitados e recebidos
A16: 🗄️ BASE GESTRAN
A19: Posição completa do sistema, todos os 5.480 itens
A21: 📊 ANALISAR DADOS
A24: Visão geral: itens zerados, duplicados, valor parado
A25: HISTÓRICO DE SAÍDA

Sheet Controle_Estoque
A1: CONTROLE DE ESTOQUE — O QUE COMPRAR | F1: ITENS P/ COMPRAR AGORA: | H1: =COUNTIF(G8:G44,"COMPRAR") -> 30
A2: Uma linha por produto. Preencha Produto + Setor (nome exato da Base_Gestran) e Mínimo/Máximo — o resto roda sozinho. Sem duplicar: cada item aparece uma vez só. | F2: ITENS OK / ACIMA DO MÁXIMO: | H2: =COUNTIF(G8:G44,"OK")+COUNTIF(G8:G44,"ACIMA DO MÁXIMO") -> 7
A4: Regra: quando Saldo Atual ≤ Mínimo, o Status vira COMPRAR e sugere repor até o Máximo.
A7: Produto | B7: Setor / Almoxarifado | C7: Saldo Atual (sistema) | D7: Consumo Médio Semanal (referência) | E7: Mínimo (você define) | F7: Máximo (você define) | G7: Status | H7: Qtd Sugerida de Compra | I7: Observações
A8: LAMPADA H4 24V PHILLIPS | B8: ALMOXARIFADO | C8: =IF(A8="","",SUMIFS(Base_Gestran!$E$2:$E$5481,Base_Gestran!$A$2:$A$5481,A8,Base_Gestran!$C$2:$C$5481,B8)) -> 1 | D8: =IF(A8="","",IF(SUMIFS(Historico_Saidas!$D$6:$D$5000,Historico_Saidas!$A$6:$A$5000,A8,Historico_Saidas!$B$6:$B$5000,B8)=0,"",SUMIFS(Historico_Saidas!$D$6:$D$5000,Historico_Saidas!$A$6:$A$5000,A8,Historico_Saidas!$B$6:$B$5000,B8)/Historico_Saidas!$G$1)) -> 2.3939503 | E8: 1 | F8: 3 | G8: =IF(OR(A8="",C8="",E8=""),"",IF(C8<=E8,"COMPRAR",IF(C8>F8,"ACIMA DO MÁXIMO","OK"))) -> COMPRAR | H8: =IF(G8="COMPRAR",MAX(F8-C8,0),0) -> 2
A9: LAMPADA H7 24V PHILLIPS | B9: ALMOXARIFADO | C9: =IF(A9="","",SUMIFS(Base_Gestran!$E$2:$E$5481,Base_Gestran!$A$2:$A$5481,A9,Base_Gestran!$C$2:$C$5481,B9)) -> 8 | D9: =IF(A9="","",IF(SUMIFS(Historico_Saidas!$D$6:$D$5000,Historico_Saidas!$A$6:$A$5000,A9,Historico_Saidas!$B$6:$B$5000,B9)=0,"",SUMIFS(Historico_Saidas!$D$6:$D$5000,Historico_Saidas!$A$6:$A$5000,A9,Historico_Saidas!$B$6:$B$5000,B9)/Historico_Saidas!$G$1)) -> 2.0362336 | E9: 1 | F9: 3 | G9: =IF(OR(A9="",C9="",E9=""),"",IF(C9<=E9,"COMPRAR",IF(C9>F9,"ACIMA DO MÁXIMO","OK"))) -> ACIMA DO MÁXIMO | H9: =IF(G9="COMPRAR",MAX(F9-C9,0),0) -> 0
A10: BUZINA BIBI 24V | B10: ALMOXARIFADO | C10: =IF(A10="","",SUMIFS(Base_Gestran!$E$2:$E$5481,Base_Gestran!$A$2:$A$5481,A10,Base_Gestran!$C$2:$C$5481,B10)) -> 1 | D10: =IF(A10="","",IF(SUMIFS(Historico_Saidas!$D$6:$D$5000,Historico_Saidas!$A$6:$A$5000,A10,Historico_Saidas!$B$6:$B$5000,B10)=0,"",SUMIFS(Historico_Saidas!$D$6:$D$5000,Historico_Saidas!$A$6:$A$5000,A10,Historico_Saidas!$B$6:$B$5000,B10)/Historico_Saidas!$G$1)) -> 0.60536673 | E10: 2 | F10: 4 | G10: =IF(OR(A10="",C10="",E10=""),"",IF(C10<=E10,"COMPRAR",IF(C10>F10,"ACIMA DO MÁXIMO","OK"))) -> COMPRAR | H10: =IF(G10="COMPRAR",MAX(F10-C10,0),0) -> 3
A11: RESERVATORIO DE ÁGUA ACCELO TANQUE EXPANSÃO PARALELA | B11: ALMOXARIFADO | C11: =IF(A11="","",SUMIFS(Base_Gestran!$E$2:$E$5481,Base_Gestran!$A$2:$A$5481,A11,Base_Gestran!$C$2:$C$5481,B11)) -> 4 | D11: =IF(A11="","",IF(SUMIFS(Historico_Saidas!$D$6:$D$5000,Historico_Saidas!$A$6:$A$5000,A11,Historico_Saidas!$B$6:$B$5000,B11)=0,"",SUMIFS(Historico_Saidas!$D$6:$D$5000,Historico_Saidas!$A$6:$A$5000,A11,Historico_Saidas!$B$6:$B$5000,B11)/Historico_Saidas!$G$1)) -> 0.19261669 | E11: 1 | F11: 2 | G11: =IF(OR(A11="",C11="",E11=""),"",IF(C11<=E11,"COMPRAR",IF(C11>F11,"ACIMA DO MÁXIMO","OK"))) -> ACIMA DO MÁXIMO | H11: =IF(G11="COMPRAR",MAX(F11-C11,0),0) -> 0
A12: ROLAMENTO DE CENTRO 45MM | B12: ALMOXARIFADO | C12: =IF(A12="","",SUMIFS(Base_Gestran!$E$2:$E$5481,Base_Gestran!$A$2:$A$5481,A12,Base_Gestran!$C$2:$C$5481,B12)) -> 0 | D12: =IF(A12="","",IF(SUMIFS(Historico_Saidas!$D$6:$D$5000,Historico_Saidas!$A$6:$A$5000,A12,Historico_Saidas!$B$6:$B$5000,B12)=0,"",SUMIFS(Historico_Saidas!$D$6:$D$5000,Historico_Saidas!$A$6:$A$5000,A12,Historico_Saidas!$B$6:$B$5000,B12)/Historico_Saidas!$G$1)) -> 0.082550009 | E12: 1 | F12: 3 | G12: =IF(OR(A12="",C12="",E12=""),"",IF(C12<=E12,"COMPRAR",IF(C12>F12,"ACIMA DO MÁXIMO","OK"))) -> COMPRAR | H12: =IF(G12="COMPRAR",MAX(F12-C12,0),0) -> 3
A13: TANQUE DE LIQUIDO SA1 AC/AE | B13: ALMOXARIFADO | C13: =IF(A13="","",SUMIFS(Base_Gestran!$E$2:$E$5481,Base_Gestran!$A$2:$A$5481,A13,Base_Gestran!$C$2:$C$5481,B13)) -> 1 | D13: =IF(A13="","",IF(SUMIFS(Historico_Saidas!$D$6:$D$5000,Historico_Saidas!$A$6:$A$5000,A13,Historico_Saidas!$B$6:$B$5000,B13)=0,"",SUMIFS(Historico_Saidas!$D$6:$D$5000,Historico_Saidas!$A$6:$A$5000,A13,Historico_Saidas!$B$6:$B$5000,B13)/Historico_Saidas!$G$1)) -> 0.055033339 | E13: 1 | F13: 1 | G13: =IF(OR(A13="",C13="",E13=""),"",IF(C13<=E13,"COMPRAR",IF(C13>F13,"ACIMA DO MÁXIMO","OK"))) -> COMPRAR | H13: =IF(G13="COMPRAR",MAX(F13-C13,0),0) -> 0 | I13: aguardando pra dar saida
A14: OLEO 175PZ DANFOS 160PZ | B14: ALMOXARIFADO | C14: =IF(A14="","",SUMIFS(Base_Gestran!$E$2:$E$5481,Base_Gestran!$A$2:$A$5481,A14,Base_Gestran!$C$2:$C$5481,B14)) -> 5 | D14: =IF(A14="","",IF(SUMIFS(Historico_Saidas!$D$6:$D$5000,Historico_Saidas!$A$6:$A$5000,A14,Historico_Saidas!$B$6:$B$5000,B14)=0,"",SUMIFS(Historico_Saidas!$D$6:$D$5000,Historico_Saidas!$A$6:$A$5000,A14,Historico_Saidas!$B$6:$B$5000,B14)/Historico_Saidas!$G$1)) -> 0.02751667 | E14: 1 | F14: 3 | G14: =IF(OR(A14="",C14="",E14=""),"",IF(C14<=E14,"COMPRAR",IF(C14>F14,"ACIMA DO MÁXIMO","OK"))) -> ACIMA DO MÁXIMO | H14: =IF(G14="COMPRAR",MAX(F14-C14,0),0) -> 0
A15: CONJ ALAVANCA DO CONTRA PESO DE AÇO A 0002643224 | B15: ALMOXARIFADO 1- MANUTENCAO TRANSPORTE | C15: =IF(A15="","",SUMIFS(Base_Gestran!$E$2:$E$5481,Base_Gestran!$A$2:$A$5481,A15,Base_Gestran!$C$2:$C$5481,B15)) -> 1 | D15: =IF(A15="","",IF(SUMIFS(Historico_Saidas!$D$6:$D$5000,Historico_Saidas!$A$6:$A$5000,A15,Historico_Saidas!$B$6:$B$5000,B15)=0,"",SUMIFS(Historico_Saidas!$D$6:$D$5000,Historico_Saidas!$A$6:$A$5000,A15,Historico_Saidas!$B$6:$B$5000,B15)/Historico_Saidas!$G$1)) | E15: 1 | F15: 1 | G15: =IF(OR(A15="",C15="",E15=""),"",IF(C15<=E15,"COMPRAR",IF(C15>F15,"ACIMA DO MÁXIMO","OK"))) -> COMPRAR | H15: =IF(G15="COMPRAR",MAX(F15-C15,0),0) -> 0
A16: BOMBA D'AGUA (OM 904/906) | B16: ALMOXARIFADO 1- MANUTENCAO TRANSPORTE | C16: =IF(A16="","",SUMIFS(Base_Gestran!$E$2:$E$5481,Base_Gestran!$A$2:$A$5481,A16,Base_Gestran!$C$2:$C$5481,B16)) -> 1 | D16: =IF(A16="","",IF(SUMIFS(Historico_Saidas!$D$6:$D$5000,Historico_Saidas!$A$6:$A$5000,A16,Historico_Saidas!$B$6:$B$5000,B16)=0,"",SUMIFS(Historico_Saidas!$D$6:$D$5000,Historico_Saidas!$A$6:$A$5000,A16,Historico_Saidas!$B$6:$B$5000,B16)/Historico_Saidas!$G$1)) | E16: 1 | F16: 1 | G16: =IF(OR(A16="",C16="",E16=""),"",IF(C16<=E16,"COMPRAR",IF(C16>F16,"ACIMA DO MÁXIMO","OK"))) -> COMPRAR | H16: =IF(G16="COMPRAR",MAX(F16-C16,0),0) -> 0
A17: PAPEL HIGIENICO ROLAO 8X300 | B17: ALMOXARIFADO 5- LIMPEZA | C17: =IF(A17="","",SUMIFS(Base_Gestran!$E$2:$E$5481,Base_Gestran!$A$2:$A$5481,A17,Base_Gestran!$C$2:$C$5481,B17)) -> 794 | D17: =IF(A17="","",IF(SUMIFS(Historico_Saidas!$D$6:$D$5000,Historico_Saidas!$A$6:$A$5000,A17,Historico_Saidas!$B$6:$B$5000,B17)=0,"",SUMIFS(Historico_Saidas!$D$6:$D$5000,Historico_Saidas!$A$6:$A$5000,A17,Historico_Saidas!$B$6:$B$5000,B17)/Historico_Saidas!$G$1)) -> 0.46778338 | E17: 1 | F17: 5 | G17: =IF(OR(A17="",C17="",E17=""),"",IF(C17<=E17,"COMPRAR",IF(C17>F17,"ACIMA DO MÁXIMO","OK"))) -> ACIMA DO MÁXIMO | H17: =IF(G17="COMPRAR",MAX(F17-C17,0),0) -> 0
A18: SIKAFLEX BRANCO | B18: ALMOXARIFADO | C18: =IF(A18="","",SUMIFS(Base_Gestran!$E$2:$E$5481,Base_Gestran!$A$2:$A$5481,A18,Base_Gestran!$C$2:$C$5481,B18)) -> 0 | D18: =IF(A18="","",IF(SUMIFS(Historico_Saidas!$D$6:$D$5000,Historico_Saidas!$A$6:$A$5000,A18,Historico_Saidas!$B$6:$B$5000,B18)=0,"",SUMIFS(Historico_Saidas!$D$6:$D$5000,Historico_Saidas!$A$6:$A$5000,A18,Historico_Saidas!$B$6:$B$5000,B18)/Historico_Saidas!$G$1)) | E18: 1 | F18: 2 | G18: =IF(OR(A18="",C18="",E18=""),"",IF(C18<=E18,"COMPRAR",IF(C18>F18,"ACIMA DO MÁXIMO","OK"))) -> COMPRAR | H18: =IF(G18="COMPRAR",MAX(F18-C18,0),0) -> 2
A19: RODA COLSON PNEUMATICA 350-4 R.7 | B19: ALMOXARIFADO | C19: =IF(A19="","",SUMIFS(Base_Gestran!$E$2:$E$5481,Base_Gestran!$A$2:$A$5481,A19,Base_Gestran!$C$2:$C$5481,B19)) -> 6 | D19: =IF(A19="","",IF(SUMIFS(Historico_Saidas!$D$6:$D$5000,Historico_Saidas!$A$6:$A$5000,A19,Historico_Saidas!$B$6:$B$5000,B19)=0,"",SUMIFS(Historico_Saidas!$D$6:$D$5000,Historico_Saidas!$A$6:$A$5000,A19,Historico_Saidas!$B$6:$B$5000,B19)/Historico_Saidas!$G$1)) -> 4.5952838 | E19: 2 | F19: 4 | G19: =IF(OR(A19="",C19="",E19=""),"",IF(C19<=E19,"COMPRAR",IF(C19>F19,"ACIMA DO MÁXIMO","OK"))) -> ACIMA DO MÁXIMO | H19: =IF(G19="COMPRAR",MAX(F19-C19,0),0) -> 0
A20: FITA ROTULADOR COMPATIVEL C/ TZE-641 18MM AMARELA Pt-e550wvp | B20: ALMOXARIFADO | C20: =IF(A20="","",SUMIFS(Base_Gestran!$E$2:$E$5481,Base_Gestran!$A$2:$A$5481,A20,Base_Gestran!$C$2:$C$5481,B20)) -> 0 | D20: =IF(A20="","",IF(SUMIFS(Historico_Saidas!$D$6:$D$5000,Historico_Saidas!$A$6:$A$5000,A20,Historico_Saidas!$B$6:$B$5000,B20)=0,"",SUMIFS(Historico_Saidas!$D$6:$D$5000,Historico_Saidas!$A$6:$A$5000,A20,Historico_Saidas!$B$6:$B$5000,B20)/Historico_Saidas!$G$1)) | E20: 4 | F20: 8 | G20: =IF(OR(A20="",C20="",E20=""),"",IF(C20<=E20,"COMPRAR",IF(C20>F20,"ACIMA DO MÁXIMO","OK"))) -> COMPRAR | H20: =IF(G20="COMPRAR",MAX(F20-C20,0),0) -> 8
A21: ANTISSEPTICO BUCAL REFIL 1 LITRO | B21: ALMOXARIFADO | C21: =IF(A21="","",SUMIFS(Base_Gestran!$E$2:$E$5481,Base_Gestran!$A$2:$A$5481,A21,Base_Gestran!$C$2:$C$5481,B21)) -> 1 | D21: =IF(A21="","",IF(SUMIFS(Historico_Saidas!$D$6:$D$5000,Historico_Saidas!$A$6:$A$5000,A21,Historico_Saidas!$B$6:$B$5000,B21)=0,"",SUMIFS(Historico_Saidas!$D$6:$D$5000,Historico_Saidas!$A$6:$A$5000,A21,Historico_Saidas!$B$6:$B$5000,B21)/Historico_Saidas!$G$1)) -> 0.41275005 | E21: 5 | F21: 9 | G21: =IF(OR(A21="",C21="",E21=""),"",IF(C21<=E21,"COMPRAR",IF(C21>F21,"ACIMA DO MÁXIMO","OK"))) -> COMPRAR | H21: =IF(G21="COMPRAR",MAX(F21-C21,0),0) -> 8
A22: PEDRA PERFUMADA SANÍTARIA (REDE PLÁSTICA) HARPIC | B22: ALMOXARIFADO | C22: =IF(A22="","",SUMIFS(Base_Gestran!$E$2:$E$5481,Base_Gestran!$A$2:$A$5481,A22,Base_Gestran!$C$2:$C$5481,B22)) -> 0 | D22: =IF(A22="","",IF(SUMIFS(Historico_Saidas!$D$6:$D$5000,Historico_Saidas!$A$6:$A$5000,A22,Historico_Saidas!$B$6:$B$5000,B22)=0,"",SUMIFS(Historico_Saidas!$D$6:$D$5000,Historico_Saidas!$A$6:$A$5000,A22,Historico_Saidas!$B$6:$B$5000,B22)/Historico_Saidas!$G$1)) | E22: 6 | F22: 10 | G22: =IF(OR(A22="",C22="",E22=""),"",IF(C22<=E22,"COMPRAR",IF(C22>F22,"ACIMA DO MÁXIMO","OK"))) -> COMPRAR | H22: =IF(G22="COMPRAR",MAX(F22-C22,0),0) -> 10
A23: PERFEX | B23: ALMOXARIFADO | C23: =IF(A23="","",SUMIFS(Base_Gestran!$E$2:$E$5481,Base_Gestran!$A$2:$A$5481,A23,Base_Gestran!$C$2:$C$5481,B23)) -> 0 | D23: =IF(A23="","",IF(SUMIFS(Historico_Saidas!$D$6:$D$5000,Historico_Saidas!$A$6:$A$5000,A23,Historico_Saidas!$B$6:$B$5000,B23)=0,"",SUMIFS(Historico_Saidas!$D$6:$D$5000,Historico_Saidas!$A$6:$A$5000,A23,Historico_Saidas!$B$6:$B$5000,B23)/Historico_Saidas!$G$1)) | E23: 7 | F23: 11 | G23: =IF(OR(A23="",C23="",E23=""),"",IF(C23<=E23,"COMPRAR",IF(C23>F23,"ACIMA DO MÁXIMO","OK"))) -> COMPRAR | H23: =IF(G23="COMPRAR",MAX(F23-C23,0),0) -> 11
A24: PAPEL HIGIENICO ROLAO 8X300 | B24: ALMOXARIFADO 5- LIMPEZA | C24: =IF(A24="","",SUMIFS(Base_Gestran!$E$2:$E$5481,Base_Gestran!$A$2:$A$5481,A24,Base_Gestran!$C$2:$C$5481,B24)) -> 794 | D24: =IF(A24="","",IF(SUMIFS(Historico_Saidas!$D$6:$D$5000,Historico_Saidas!$A$6:$A$5000,A24,Historico_Saidas!$B$6:$B$5000,B24)=0,"",SUMIFS(Historico_Saidas!$D$6:$D$5000,Historico_Saidas!$A$6:$A$5000,A24,Historico_Saidas!$B$6:$B$5000,B24)/Historico_Saidas!$G$1)) -> 0.46778338 | E24: 8 | F24: 12 | G24: =IF(OR(A24="",C24="",E24=""),"",IF(C24<=E24,"COMPRAR",IF(C24>F24,"ACIMA DO MÁXIMO","OK"))) -> ACIMA DO MÁXIMO | H24: =IF(G24="COMPRAR",MAX(F24-C24,0),0) -> 0
A25: BATERIA 100A (USAMOS A VELHA COMO BASE DE TROCA PARA ABATER NO VALOR) | B25: ALMOXARIFADO | C25: =IF(A25="","",SUMIFS(Base_Gestran!$E$2:$E$5481,Base_Gestran!$A$2:$A$5481,A25,Base_Gestran!$C$2:$C$5481,B25)) -> 0 | D25: =IF(A25="","",IF(SUMIFS(Historico_Saidas!$D$6:$D$5000,Historico_Saidas!$A$6:$A$5000,A25,Historico_Saidas!$B$6:$B$5000,B25)=0,"",SUMIFS(Historico_Saidas!$D$6:$D$5000,Historico_Saidas!$A$6:$A$5000,A25,Historico_Saidas!$B$6:$B$5000,B25)/Historico_Saidas!$G$1)) | E25: 9 | F25: 13 | G25: =IF(OR(A25="",C25="",E25=""),"",IF(C25<=E25,"COMPRAR",IF(C25>F25,"ACIMA DO MÁXIMO","OK"))) -> COMPRAR | H25: =IF(G25="COMPRAR",MAX(F25-C25,0),0) -> 13
... A48: LANTERNA LATERAL LED REDONDA VER/LAR/CRISTAL | B48: ALMOXARIFADO | C48: =IF(A48="","",SUMIFS(Base_Gestran!$E$2:$E$5481,Base_Gestran!$A$2:$A$5481,A48,Base_Gestran!$C$2:$C$5481,B48)) -> 5 | D48: =IF(A48="","",IF(SUMIFS(Historico_Saidas!$D$6:$D$5000,Historico_Saidas!$A$6:$A$5000,A48,Historico_Saidas!$B$6:$B$5000,B48)=0,"",SUMIFS(Historico_Saidas!$D$6:$D$5000,Historico_Saidas!$A$6:$A$5000,A48,Historico_Saidas!$B$6:$B$5000,B48)/Historico_Saidas!$G$1)) -> 1.7610669 | E48: 32 | F48: 36 | G48: =IF(OR(A48="",C48="",E48=""),"",IF(C48<=E48,"COMPRAR",IF(C48>F48,"ACIMA DO MÁXIMO","OK"))) -> COMPRAR | H48: =IF(G48="COMPRAR",MAX(F48-C48,0),0) -> 31
A49: DUREX PACOTES COM 5 | C49: =IF(A49="","",SUMIFS(Base_Gestran!$E$2:$E$5481,Base_Gestran!$A$2:$A$5481,A49,Base_Gestran!$C$2:$C$5481,B49)) -> 0 | D49: =IF(A49="","",IF(SUMIFS(Historico_Saidas!$D$6:$D$5000,Historico_Saidas!$A$6:$A$5000,A49,Historico_Saidas!$B$6:$B$5000,B49)=0,"",SUMIFS(Historico_Saidas!$D$6:$D$5000,Historico_Saidas!$A$6:$A$5000,A49,Historico_Saidas!$B$6:$B$5000,B49)/Historico_Saidas!$G$1)) | G49: =IF(OR(A49="",C49="",E49=""),"",IF(C49<=E49,"COMPRAR",IF(C49>F49,"ACIMA DO MÁXIMO","OK"))) | H49: =IF(G49="COMPRAR",MAX(F49-C49,0),0) -> 0
A50: SACOLA COM ALÇA 50X60 | C50: =IF(A50="","",SUMIFS(Base_Gestran!$E$2:$E$5481,Base_Gestran!$A$2:$A$5481,A50,Base_Gestran!$C$2:$C$5481,B50)) -> 0 | D50: =IF(A50="","",IF(SUMIFS(Historico_Saidas!$D$6:$D$5000,Historico_Saidas!$A$6:$A$5000,A50,Historico_Saidas!$B$6:$B$5000,B50)=0,"",SUMIFS(Historico_Saidas!$D$6:$D$5000,Historico_Saidas!$A$6:$A$5000,A50,Historico_Saidas!$B$6:$B$5000,B50)/Historico_Saidas!$G$1)) | G50: =IF(OR(A50="",C50="",E50=""),"",IF(C50<=E50,"COMPRAR",IF(C50>F50,"ACIMA DO MÁXIMO","OK"))) | H50: =IF(G50="COMPRAR",MAX(F50-C50,0),0) -> 0
A51: STRECTH | C51: =IF(A51="","",SUMIFS(Base_Gestran!$E$2:$E$5481,Base_Gestran!$A$2:$A$5481,A51,Base_Gestran!$C$2:$C$5481,B51)) -> 0 | D51: =IF(A51="","",IF(SUMIFS(Historico_Saidas!$D$6:$D$5000,Historico_Saidas!$A$6:$A$5000,A51,Historico_Saidas!$B$6:$B$5000,B51)=0,"",SUMIFS(Historico_Saidas!$D$6:$D$5000,Historico_Saidas!$A$6:$A$5000,A51,Historico_Saidas!$B$6:$B$5000,B51)/Historico_Saidas!$G$1)) | G51: =IF(OR(A51="",C51="",E51=""),"",IF(C51<=E51,"COMPRAR",IF(C51>F51,"ACIMA DO MÁXIMO","OK"))) | H51: =IF(G51="COMPRAR",MAX(F51-C51,0),0) -> 0
A52: RESMA A4 | C52: =IF(A52="","",SUMIFS(Base_Gestran!$E$2:$E$5481,Base_Gestran!$A$2:$A$5481,A52,Base_Gestran!$C$2:$C$5481,B52)) -> 0 | D52: =IF(A52="","",IF(SUMIFS(Historico_Saidas!$D$6:$D$5000,Historico_Saidas!$A$6:$A$5000,A52,Historico_Saidas!$B$6:$B$5000,B52)=0,"",SUMIFS(Historico_Saidas!$D$6:$D$5000,Historico_Saidas!$A$6:$A$5000,A52,Historico_Saidas!$B$6:$B$5000,B52)/Historico_Saidas!$G$1)) | G52: =IF(OR(A52="",C52="",E52=""),"",IF(C52<=E52,"COMPRAR",IF(C52>F52,"ACIMA DO MÁXIMO","OK"))) | H52: =IF(G52="COMPRAR",MAX(F52-C52,0),0) -> 0
A53: LUVA | C53: =IF(A53="","",SUMIFS(Base_Gestran!$E$2:$E$5481,Base_Gestran!$A$2:$A$5481,A53,Base_Gestran!$C$2:$C$5481,B53)) -> 0 | D53: =IF(A53="","",IF(SUMIFS(Historico_Saidas!$D$6:$D$5000,Historico_Saidas!$A$6:$A$5000,A53,Historico_Saidas!$B$6:$B$5000,B53)=0,"",SUMIFS(Historico_Saidas!$D$6:$D$5000,Historico_Saidas!$A$6:$A$5000,A53,Historico_Saidas!$B$6:$B$5000,B53)/Historico_Saidas!$G$1)) | G53: =IF(OR(A53="",C53="",E53=""),"",IF(C53<=E53,"COMPRAR",IF(C53>F53,"ACIMA DO MÁXIMO","OK"))) | H53: =IF(G53="COMPRAR",MAX(F53-C53,0),0) -> 0
A54: CORDA P/BOI | C54: =IF(A54="","",SUMIFS(Base_Gestran!$E$2:$E$5481,Base_Gestran!$A$2:$A$5481,A54,Base_Gestran!$C$2:$C$5481,B54)) -> 0 | D54: =IF(A54="","",IF(SUMIFS(Historico_Saidas!$D$6:$D$5000,Historico_Saidas!$A$6:$A$5000,A54,Historico_Saidas!$B$6:$B$5000,B54)=0,"",SUMIFS(Historico_Saidas!$D$6:$D$5000,Historico_Saidas!$A$6:$A$5000,A54,Historico_Saidas!$B$6:$B$5000,B54)/Historico_Saidas!$G$1)) | G54: =IF(OR(A54="",C54="",E54=""),"",IF(C54<=E54,"COMPRAR",IF(C54>F54,"ACIMA DO MÁXIMO","OK"))) | H54: =IF(G54="COMPRAR",MAX(F54-C54,0),0) -> 0
A55: CORDA AMARRAR CAMINHﾃグ | C55: =IF(A55="","",SUMIFS(Base_Gestran!$E$2:$E$5481,Base_Gestran!$A$2:$A$5481,A55,Base_Gestran!$C$2:$C$5481,B55)) -> 0 | D55: =IF(A55="","",IF(SUMIFS(Historico_Saidas!$D$6:$D$5000,Historico_Saidas!$A$6:$A$5000,A55,Historico_Saidas!$B$6:$B$5000,B55)=0,"",SUMIFS(Historico_Saidas!$D$6:$D$5000,Historico_Saidas!$A$6:$A$5000,A55,Historico_Saidas!$B$6:$B$5000,B55)/Historico_Saidas!$G$1)) | G55: =IF(OR(A55="",C55="",E55=""),"",IF(C55<=E55,"COMPRAR",IF(C55>F55,"ACIMA DO MÁXIMO","OK"))) | H55: =IF(G55="COMPRAR",MAX(F55-C55,0),0) -> 0
A56: PARAFUSO DE CAIXA | C56: =IF(A56="","",SUMIFS(Base_Gestran!$E$2:$E$5481,Base_Gestran!$A$2:$A$5481,A56,Base_Gestran!$C$2:$C$5481,B56)) -> 0 | D56: =IF(A56="","",IF(SUMIFS(Historico_Saidas!$D$6:$D$5000,Historico_Saidas!$A$6:$A$5000,A56,Historico_Saidas!$B$6:$B$5000,B56)=0,"",SUMIFS(Historico_Saidas!$D$6:$D$5000,Historico_Saidas!$A$6:$A$5000,A56,Historico_Saidas!$B$6:$B$5000,B56)/Historico_Saidas!$G$1)) | G56: =IF(OR(A56="",C56="",E56=""),"",IF(C56<=E56,"COMPRAR",IF(C56>F56,"ACIMA DO MÁXIMO","OK"))) | H56: =IF(G56="COMPRAR",MAX(F56-C56,0),0) -> 0
C57: =IF(A57="","",SUMIFS(Base_Gestran!$E$2:$E$5481,Base_Gestran!$A$2:$A$5481,A57,Base_Gestran!$C$2:$C$5481,B57)) | D57: =IF(A57="","",IF(SUMIFS(Historico_Saidas!$D$6:$D$5000,Historico_Saidas!$A$6:$A$5000,A57,Historico_Saidas!$B$6:$B$5000,B57)=0,"",SUMIFS(Historico_Saidas!$D$6:$D$5000,Historico_Saidas!$A$6:$A$5000,A57,Historico_Saidas!$B$6:$B$5000,B57)/Historico_Saidas!$G$1)) | G57: =IF(OR(A57="",C57="",E57=""),"",IF(C57<=E57,"COMPRAR",IF(C57>F57,"ACIMA DO MÁXIMO","OK"))) | H57: =IF(G57="COMPRAR",MAX(F57-C57,0),0) -> 0
C58: =IF(A58="","",SUMIFS(Base_Gestran!$E$2:$E$5481,Base_Gestran!$A$2:$A$5481,A58,Base_Gestran!$C$2:$C$5481,B58)) | D58: =IF(A58="","",IF(SUMIFS(Historico_Saidas!$D$6:$D$5000,Historico_Saidas!$A$6:$A$5000,A58,Historico_Saidas!$B$6:$B$5000,B58)=0,"",SUMIFS(Historico_Saidas!$D$6:$D$5000,Historico_Saidas!$A$6:$A$5000,A58,Historico_Saidas!$B$6:$B$5000,B58)/Historico_Saidas!$G$1)) | G58: =IF(OR(A58="",C58="",E58=""),"",IF(C58<=E58,"COMPRAR",IF(C58>F58,"ACIMA DO MÁXIMO","OK"))) | H58: =IF(G58="COMPRAR",MAX(F58-C58,0),0) -> 0
C59: =IF(A59="","",SUMIFS(Base_Gestran!$E$2:$E$5481,Base_Gestran!$A$2:$A$5481,A59,Base_Gestran!$C$2:$C$5481,B59)) | D59: =IF(A59="","",IF(SUMIFS(Historico_Saidas!$D$6:$D$5000,Historico_Saidas!$A$6:$A$5000,A59,Historico_Saidas!$B$6:$B$5000,B59)=0,"",SUMIFS(Historico_Saidas!$D$6:$D$5000,Historico_Saidas!$A$6:$A$5000,A59,Historico_Saidas!$B$6:$B$5000,B59)/Historico_Saidas!$G$1)) | G59: =IF(OR(A59="",C59="",E59=""),"",IF(C59<=E59,"COMPRAR",IF(C59>F59,"ACIMA DO MÁXIMO","OK"))) | H59: =IF(G59="COMPRAR",MAX(F59-C59,0),0) -> 0
C60: =IF(A60="","",SUMIFS(Base_Gestran!$E$2:$E$5481,Base_Gestran!$A$2:$A$5481,A60,Base_Gestran!$C$2:$C$5481,B60)) | D60: =IF(A60="","",IF(SUMIFS(Historico_Saidas!$D$6:$D$5000,Historico_Saidas!$A$6:$A$5000,A60,Historico_Saidas!$B$6:$B$5000,B60)=0,"",SUMIFS(Historico_Saidas!$D$6:$D$5000,Historico_Saidas!$A$6:$A$5000,A60,Historico_Saidas!$B$6:$B$5000,B60)/Historico_Saidas!$G$1)) | G60: =IF(OR(A60="",C60="",E60=""),"",IF(C60<=E60,"COMPRAR",IF(C60>F60,"ACIMA DO MÁXIMO","OK"))) | H60: =IF(G60="COMPRAR",MAX(F60-C60,0),0) -> 0
C61: =IF(A61="","",SUMIFS(Base_Gestran!$E$2:$E$5481,Base_Gestran!$A$2:$A$5481,A61,Base_Gestran!$C$2:$C$5481,B61)) | D61: =IF(A61="","",IF(SUMIFS(Historico_Saidas!$D$6:$D$5000,Historico_Saidas!$A$6:$A$5000,A61,Historico_Saidas!$B$6:$B$5000,B61)=0,"",SUMIFS(Historico_Saidas!$D$6:$D$5000,Historico_Saidas!$A$6:$A$5000,A61,Historico_Saidas!$B$6:$B$5000,B61)/Historico_Saidas!$G$1)) | G61: =IF(OR(A61="",C61="",E61=""),"",IF(C61<=E61,"COMPRAR",IF(C61>F61,"ACIMA DO MÁXIMO","OK"))) | H61: =IF(G61="COMPRAR",MAX(F61-C61,0),0) -> 0
C62: =IF(A62="","",SUMIFS(Base_Gestran!$E$2:$E$5481,Base_Gestran!$A$2:$A$5481,A62,Base_Gestran!$C$2:$C$5481,B62)) | D62: =IF(A62="","",IF(SUMIFS(Historico_Saidas!$D$6:$D$5000,Historico_Saidas!$A$6:$A$5000,A62,Historico_Saidas!$B$6:$B$5000,B62)=0,"",SUMIFS(Historico_Saidas!$D$6:$D$5000,Historico_Saidas!$A$6:$A$5000,A62,Historico_Saidas!$B$6:$B$5000,B62)/Historico_Saidas!$G$1)) | G62: =IF(OR(A62="",C62="",E62=""),"",IF(C62<=E62,"COMPRAR",IF(C62>F62,"ACIMA DO MÁXIMO","OK"))) | H62: =IF(G62="COMPRAR",MAX(F62-C62,0),0) -> 0
C63: =IF(A63="","",SUMIFS(Base_Gestran!$E$2:$E$5481,Base_Gestran!$A$2:$A$5481,A63,Base_Gestran!$C$2:$C$5481,B63)) | D63: =IF(A63="","",IF(SUMIFS(Historico_Saidas!$D$6:$D$5000,Historico_Saidas!$A$6:$A$5000,A63,Historico_Saidas!$B$6:$B$5000,B63)=0,"",SUMIFS(Historico_Saidas!$D$6:$D$5000,Historico_Saidas!$A$6:$A$5000,A63,Historico_Saidas!$B$6:$B$5000,B63)/Historico_Saidas!$G$1)) | G63: =IF(OR(A63="",C63="",E63=""),"",IF(C63<=E63,"COMPRAR",IF(C63>F63,"ACIMA DO MÁXIMO","OK"))) | H63: =IF(G63="COMPRAR",MAX(F63-C63,0),0) -> 0
C64: =IF(A64="","",SUMIFS(Base_Gestran!$E$2:$E$5481,Base_Gestran!$A$2:$A$5481,A64,Base_Gestran!$C$2:$C$5481,B64)) | D64: =IF(A64="","",IF(SUMIFS(Historico_Saidas!$D$6:$D$5000,Historico_Saidas!$A$6:$A$5000,A64,Historico_Saidas!$B$6:$B$5000,B64)=0,"",SUMIFS(Historico_Saidas!$D$6:$D$5000,Historico_Saidas!$A$6:$A$5000,A64,Historico_Saidas!$B$6:$B$5000,B64)/Historico_Saidas!$G$1)) | G64: =IF(OR(A64="",C64="",E64=""),"",IF(C64<=E64,"COMPRAR",IF(C64>F64,"ACIMA DO MÁXIMO","OK"))) | H64: =IF(G64="COMPRAR",MAX(F64-C64,0),0) -> 0
C65: =IF(A65="","",SUMIFS(Base_Gestran!$E$2:$E$5481,Base_Gestran!$A$2:$A$5481,A65,Base_Gestran!$C$2:$C$5481,B65)) | D65: =IF(A65="","",IF(SUMIFS(Historico_Saidas!$D$6:$D$5000,Historico_Saidas!$A$6:$A$5000,A65,Historico_Saidas!$B$6:$B$5000,B65)=0,"",SUMIFS(Historico_Saidas!$D$6:$D$5000,Historico_Saidas!$A$6:$A$5000,A65,Historico_Saidas!$B$6:$B$5000,B65)/Historico_Saidas!$G$1)) | G65: =IF(OR(A65="",C65="",E65=""),"",IF(C65<=E65,"COMPRAR",IF(C65>F65,"ACIMA DO MÁXIMO","OK"))) | H65: =IF(G65="COMPRAR",MAX(F65-C65,0),0) -> 0
C66: =IF(A66="","",SUMIFS(Base_Gestran!$E$2:$E$5481,Base_Gestran!$A$2:$A$5481,A66,Base_Gestran!$C$2:$C$5481,B66)) | D66: =IF(A66="","",IF(SUMIFS(Historico_Saidas!$D$6:$D$5000,Historico_Saidas!$A$6:$A$5000,A66,Historico_Saidas!$B$6:$B$5000,B66)=0,"",SUMIFS(Historico_Saidas!$D$6:$D$5000,Historico_Saidas!$A$6:$A$5000,A66,Historico_Saidas!$B$6:$B$5000,B66)/Historico_Saidas!$G$1)) | G66: =IF(OR(A66="",C66="",E66=""),"",IF(C66<=E66,"COMPRAR",IF(C66>F66,"ACIMA DO MÁXIMO","OK"))) | H66: =IF(G66="COMPRAR",MAX(F66-C66,0),0) -> 0
C67: =IF(A67="","",SUMIFS(Base_Gestran!$E$2:$E$5481,Base_Gestran!$A$2:$A$5481,A67,Base_Gestran!$C$2:$C$5481,B67)) | D67: =IF(A67="","",IF(SUMIFS(Historico_Saidas!$D$6:$D$5000,Historico_Saidas!$A$6:$A$5000,A67,Historico_Saidas!$B$6:$B$5000,B67)=0,"",SUMIFS(Historico_Saidas!$D$6:$D$5000,Historico_Saidas!$A$6:$A$5000,A67,Historico_Saidas!$B$6:$B$5000,B67)/Historico_Saidas!$G$1)) | G67: =IF(OR(A67="",C67="",E67=""),"",IF(C67<=E67,"COMPRAR",IF(C67>F67,"ACIMA DO MÁXIMO","OK"))) | H67: =IF(G67="COMPRAR",MAX(F67-C67,0),0) -> 0

Sheet Historico_Pedidos
A1: HISTÓRICO DE PEDIDOS DE COMPRA | H1: PENDENTES: | J1: =COUNTIF(I5:I60,"PENDENTE") -> 32
A2: Registro de cada solicitação: o que foi pedido, motivo, saldo no sistema, fornecedor e status até a entrega. | H2: SOLICITADOS: | J2: =COUNTIF(I5:I60,"SOLICITADO") -> 3
I3: RECEBIDOS: | J3: =COUNTIF(I5:I60,"RECEBIDO") -> 3
A4: Data do Pedido | B4: Produto / Material | C4: Quantidade a Comprar | D4: Medida (Un/Caixa/Pct) | E4: Setor | F4: Motivo | G4: Saldo Atual (sistema) | H4: Fornecedor | I4: Situação | J4: Previsão de Entrega | K4: Observações | L4: Chave (aux)
A5: 46261 | B5: SIKAFLEX BRANCO | C5: 2 | D5: UND | E5: =IF(B5="","",IFERROR(INDEX(Base_Gestran!$C$2:$C$5481,MATCH(B5,Base_Gestran!$A$2:$A$5481,0)),"NÃO CADASTRADO")) -> NÃO CADASTRADO | F5: ESTOQUE ZERADO | G5: =IF(B5="","",SUMIFS(Base_Gestran!$E$2:$E$5481,Base_Gestran!$A$2:$A$5481,B5,Base_Gestran!$C$2:$C$5481,E5)) -> 0 | H5: CASA DO PEDREIRO | I5: PENDENTE | L5: =IF(B5="","",B5&"|"&TEXT(A5,"0")) -> SIKAFLEX BRANCO|46261
A6: 46261 | B6: FITA ROTULADOR COMPATIVEL C/ TZE-641 18MM AMARELA Pt-e550wvp | C6: 2 | D6: UND | E6: =IF(B6="","",IFERROR(INDEX(Base_Gestran!$C$2:$C$5481,MATCH(B6,Base_Gestran!$A$2:$A$5481,0)),"NÃO CADASTRADO")) -> NÃO CADASTRADO | F6: ESTOQUE ZERADO | G6: =IF(B6="","",SUMIFS(Base_Gestran!$E$2:$E$5481,Base_Gestran!$A$2:$A$5481,B6,Base_Gestran!$C$2:$C$5481,E6)) -> 0 | H6: MERCADO LIVRE | I6: PENDENTE | L6: =IF(B6="","",B6&"|"&TEXT(A6,"0")) -> FITA ROTULADOR COMPATIVEL C/ TZE-641 18MM AMARELA Pt-e550wvp|46261
A7: 46261 | B7: ANTISSEPTICO BUCAL REFIL 1 LITRO | C7: 2 | D7: UND | E7: =IF(B7="","",IFERROR(INDEX(Base_Gestran!$C$2:$C$5481,MATCH(B7,Base_Gestran!$A$2:$A$5481,0)),"NÃO CADASTRADO")) -> ALMOXARIFADO | F7: ESTOQUE BAIXO | G7: =IF(B7="","",SUMIFS(Base_Gestran!$E$2:$E$5481,Base_Gestran!$A$2:$A$5481,B7,Base_Gestran!$C$2:$C$5481,E7)) -> 1 | H7: MERCADO LIVRE | I7: PENDENTE | L7: =IF(B7="","",B7&"|"&TEXT(A7,"0")) -> ANTISSEPTICO BUCAL REFIL 1 LITRO|46261
A8: 46261 | B8: PEDRA PERFUMADA SANÍTARIA (REDE PLÁSTICA) HARPIC | C8: 10 | D8: UND | E8: =IF(B8="","",IFERROR(INDEX(Base_Gestran!$C$2:$C$5481,MATCH(B8,Base_Gestran!$A$2:$A$5481,0)),"NÃO CADASTRADO")) -> NÃO CADASTRADO | F8: ESTOQUE BAIXO | G8: =IF(B8="","",SUMIFS(Base_Gestran!$E$2:$E$5481,Base_Gestran!$A$2:$A$5481,B8,Base_Gestran!$C$2:$C$5481,E8)) -> 0 | H8: JAÉ ILHA DESCARTÁVEIS | I8: PENDENTE | L8: =IF(B8="","",B8&"|"&TEXT(A8,"0")) -> PEDRA PERFUMADA SANÍTARIA (REDE PLÁSTICA) HARPIC |46261
A9: 46261 | B9: PERFEX | C9: 2 | D9: RL | E9: =IF(B9="","",IFERROR(INDEX(Base_Gestran!$C$2:$C$5481,MATCH(B9,Base_Gestran!$A$2:$A$5481,0)),"NÃO CADASTRADO")) -> NÃO CADASTRADO | F9: ESTOQUE BAIXO | G9: =IF(B9="","",SUMIFS(Base_Gestran!$E$2:$E$5481,Base_Gestran!$A$2:$A$5481,B9,Base_Gestran!$C$2:$C$5481,E9)) -> 0 | H9: JAÉ ILHA DESCARTÁVEIS | I9: PENDENTE | L9: =IF(B9="","",B9&"|"&TEXT(A9,"0")) -> PERFEX |46261
A10: 46266 | B10: PAPEL HIGIENICO ROLAO 8X300 | C10: 4 | D10: PCT | E10: =IF(B10="","",IFERROR(INDEX(Base_Gestran!$C$2:$C$5481,MATCH(B10,Base_Gestran!$A$2:$A$5481,0)),"NÃO CADASTRADO")) -> ALMOXARIFADO 5- LIMPEZA | F10: RECEBIDO | G10: =IF(B10="","",SUMIFS(Base_Gestran!$E$2:$E$5481,Base_Gestran!$A$2:$A$5481,B10,Base_Gestran!$C$2:$C$5481,E10)) -> 794 | H10: VALOIS | I10: RECEBIDO | J10: 46269 | L10: =IF(B10="","",B10&"|"&TEXT(A10,"0")) -> PAPEL HIGIENICO ROLAO 8X300|46266
A11: 46267 | B11: BATERIA 100A (USAMOS A VELHA COMO BASE DE TROCA PARA ABATER NO VALOR) | C11: 5 | D11: UND | E11: =IF(B11="","",IFERROR(INDEX(Base_Gestran!$C$2:$C$5481,MATCH(B11,Base_Gestran!$A$2:$A$5481,0)),"NÃO CADASTRADO")) -> NÃO CADASTRADO | F11: RECEBIDO | G11: =IF(B11="","",SUMIFS(Base_Gestran!$E$2:$E$5481,Base_Gestran!$A$2:$A$5481,B11,Base_Gestran!$C$2:$C$5481,E11)) -> 0 | H11: ROBSON BATERIAS | I11: RECEBIDO | J11: 46281 | L11: =IF(B11="","",B11&"|"&TEXT(A11,"0")) -> BATERIA 100A (USAMOS A VELHA COMO BASE DE TROCA PARA ABATER NO VALOR)|46267
A12: 46267 | B12: VASSOURÃO DE INOX | C12: 2 | D12: UND | E12: =IF(B12="","",IFERROR(INDEX(Base_Gestran!$C$2:$C$5481,MATCH(B12,Base_Gestran!$A$2:$A$5481,0)),"NÃO CADASTRADO")) -> NÃO CADASTRADO | F12: ESTOQUE ZERADO | G12: =IF(B12="","",SUMIFS(Base_Gestran!$E$2:$E$5481,Base_Gestran!$A$2:$A$5481,B12,Base_Gestran!$C$2:$C$5481,E12)) -> 0 | H12: MERCADO LIVRE | I12: PENDENTE | L12: =IF(B12="","",B12&"|"&TEXT(A12,"0")) -> VASSOURÃO DE INOX |46267
A13: 46267 | B13: FILTRO DE AR VW | C13: 2 | D13: UND | E13: =IF(B13="","",IFERROR(INDEX(Base_Gestran!$C$2:$C$5481,MATCH(B13,Base_Gestran!$A$2:$A$5481,0)),"NÃO CADASTRADO")) -> NÃO CADASTRADO | F13: ESTOQUE ZERADO | G13: =IF(B13="","",SUMIFS(Base_Gestran!$E$2:$E$5481,Base_Gestran!$A$2:$A$5481,B13,Base_Gestran!$C$2:$C$5481,E13)) -> 0 | H13: TRANSRIO | I13: PENDENTE | L13: =IF(B13="","",B13&"|"&TEXT(A13,"0")) -> FILTRO DE AR VW |46267
A14: 46267 | B14: FILTRO LUBRIFICANTE OMD2RO115403 VW | C14: 2 | D14: UND | E14: =IF(B14="","",IFERROR(INDEX(Base_Gestran!$C$2:$C$5481,MATCH(B14,Base_Gestran!$A$2:$A$5481,0)),"NÃO CADASTRADO")) -> NÃO CADASTRADO | F14: ESTOQUE ZERADO | G14: =IF(B14="","",SUMIFS(Base_Gestran!$E$2:$E$5481,Base_Gestran!$A$2:$A$5481,B14,Base_Gestran!$C$2:$C$5481,E14)) -> 0 | H14: TRANSRIO | I14: PENDENTE | L14: =IF(B14="","",B14&"|"&TEXT(A14,"0")) -> FILTRO LUBRIFICANTE OMD2RO115403 VW|46267
A15: 46267 | B15: FILTRO DE COMBUSTIVEL OMD2PO127177 | C15: 2 | D15: UND | E15: =IF(B15="","",IFERROR(INDEX(Base_Gestran!$C$2:$C$5481,MATCH(B15,Base_Gestran!$A$2:$A$5481,0)),"NÃO CADASTRADO")) -> ALMOXARIFADO 1- MANUTENCAO TRANSPORTE | F15: ESTOQUE BAIXO | G15: =IF(B15="","",SUMIFS(Base_Gestran!$E$2:$E$5481,Base_Gestran!$A$2:$A$5481,B15,Base_Gestran!$C$2:$C$5481,E15)) -> 4 | H15: TRANSRIO | I15: PENDENTE | L15: =IF(B15="","",B15&"|"&TEXT(A15,"0")) -> FILTRO DE COMBUSTIVEL OMD2PO127177|46267
A16: 46267 | B16: JAPONA NYLON AZUL MOTORISTA (M) | C16: 4 | D16: UND | E16: =IF(B16="","",IFERROR(INDEX(Base_Gestran!$C$2:$C$5481,MATCH(B16,Base_Gestran!$A$2:$A$5481,0)),"NÃO CADASTRADO")) -> ALMOXARIFADO 9- LOGÍSTICA | F16: ESTOQUE ZERADO | G16: =IF(B16="","",SUMIFS(Base_Gestran!$E$2:$E$5481,Base_Gestran!$A$2:$A$5481,B16,Base_Gestran!$C$2:$C$5481,E16)) -> 4 | H16: PAMCOLD | I16: PENDENTE | L16: =IF(B16="","",B16&"|"&TEXT(A16,"0")) -> JAPONA NYLON AZUL MOTORISTA (M)|46267
A17: 46267 | B17: JAPONA NYLON AZUL MOTORISTA (G) | C17: 4 | D17: UND | E17: =IF(B17="","",IFERROR(INDEX(Base_Gestran!$C$2:$C$5481,MATCH(B17,Base_Gestran!$A$2:$A$5481,0)),"NÃO CADASTRADO")) -> ALMOXARIFADO 9- LOGÍSTICA | F17: ESTOQUE ZERADO | G17: =IF(B17="","",SUMIFS(Base_Gestran!$E$2:$E$5481,Base_Gestran!$A$2:$A$5481,B17,Base_Gestran!$C$2:$C$5481,E17)) -> 6 | H17: PAMCOLD | I17: PENDENTE | L17: =IF(B17="","",B17&"|"&TEXT(A17,"0")) -> JAPONA NYLON AZUL MOTORISTA (G)|46267
A18: 46267 | B18: JAPONA NYLON AZUL MOTORISTA (GG) | C18: 4 | D18: UND | E18: =IF(B18="","",IFERROR(INDEX(Base_Gestran!$C$2:$C$5481,MATCH(B18,Base_Gestran!$A$2:$A$5481,0)),"NÃO CADASTRADO")) -> ALMOXARIFADO 9- LOGÍSTICA | F18: ESTOQUE ZERADO | G18: =IF(B18="","",SUMIFS(Base_Gestran!$E$2:$E$5481,Base_Gestran!$A$2:$A$5481,B18,Base_Gestran!$C$2:$C$5481,E18)) -> 5 | H18: PAMCOLD | I18: PENDENTE | L18: =IF(B18="","",B18&"|"&TEXT(A18,"0")) -> JAPONA NYLON AZUL MOTORISTA (GG)|46267
A19: 46267 | B19: JAPONA NYLON MOTORISTA (EGG) | C19: 2 | D19: UND | E19: =IF(B19="","",IFERROR(INDEX(Base_Gestran!$C$2:$C$5481,MATCH(B19,Base_Gestran!$A$2:$A$5481,0)),"NÃO CADASTRADO")) -> ALMOXARIFADO 9- LOGÍSTICA | F19: ESTOQUE ZERADO | G19: =IF(B19="","",SUMIFS(Base_Gestran!$E$2:$E$5481,Base_Gestran!$A$2:$A$5481,B19,Base_Gestran!$C$2:$C$5481,E19)) -> 4 | H19: PAMCOLD | I19: PENDENTE | L19: =IF(B19="","",B19&"|"&TEXT(A19,"0")) -> JAPONA NYLON MOTORISTA (EGG)|46267
A20: 46267 | B20: CALÇA TÉRMICA -25° M | C20: 4 | D20: UND | E20: =IF(B20="","",IFERROR(INDEX(Base_Gestran!$C$2:$C$5481,MATCH(B20,Base_Gestran!$A$2:$A$5481,0)),"NÃO CADASTRADO")) -> NÃO CADASTRADO | F20: ESTOQUE ZERADO | G20: =IF(B20="","",SUMIFS(Base_Gestran!$E$2:$E$5481,Base_Gestran!$A$2:$A$5481,B20,Base_Gestran!$C$2:$C$5481,E20)) -> 0 | H20: PAMCOLD | I20: PENDENTE | L20: =IF(B20="","",B20&"|"&TEXT(A20,"0")) -> CALÇA TÉRMICA -25° M|46267
A21: 46267 | B21: CALÇA TÉRMICA -25° G | C21: 4 | D21: UND | E21: =IF(B21="","",IFERROR(INDEX(Base_Gestran!$C$2:$C$5481,MATCH(B21,Base_Gestran!$A$2:$A$5481,0)),"NÃO CADASTRADO")) -> NÃO CADASTRADO | F21: ESTOQUE ZERADO | G21: =IF(B21="","",SUMIFS(Base_Gestran!$E$2:$E$5481,Base_Gestran!$A$2:$A$5481,B21,Base_Gestran!$C$2:$C$5481,E21)) -> 0 | H21: PAMCOLD | I21: PENDENTE | L21: =IF(B21="","",B21&"|"&TEXT(A21,"0")) -> CALÇA TÉRMICA -25° G|46267
A22: 46267 | B22: CALÇA TÉRMICA -25° GG | C22: 4 | D22: UND | E22: =IF(B22="","",IFERROR(INDEX(Base_Gestran!$C$2:$C$5481,MATCH(B22,Base_Gestran!$A$2:$A$5481,0)),"NÃO CADASTRADO")) -> NÃO CADASTRADO | F22: ESTOQUE ZERADO | G22: =IF(B22="","",SUMIFS(Base_Gestran!$E$2:$E$5481,Base_Gestran!$A$2:$A$5481,B22,Base_Gestran!$C$2:$C$5481,E22)) -> 0 | H22: PAMCOLD | I22: PENDENTE | L22: =IF(B22="","",B22&"|"&TEXT(A22,"0")) -> CALÇA TÉRMICA -25° GG|46267
A23: 46267 | B23: CALÇA TÉRMICA -45° M | C23: 2 | D23: UND | E23: =IF(B23="","",IFERROR(INDEX(Base_Gestran!$C$2:$C$5481,MATCH(B23,Base_Gestran!$A$2:$A$5481,0)),"NÃO CADASTRADO")) -> NÃO CADASTRADO | F23: ESTOQUE ZERADO | G23: =IF(B23="","",SUMIFS(Base_Gestran!$E$2:$E$5481,Base_Gestran!$A$2:$A$5481,B23,Base_Gestran!$C$2:$C$5481,E23)) -> 0 | H23: PAMCOLD | I23: PENDENTE | L23: =IF(B23="","",B23&"|"&TEXT(A23,"0")) -> CALÇA TÉRMICA -45° M|46267
... A30: 46282 | B30: TANQUE DE LIQUIDO SA1 AC/AE | C30: 1 | D30: UND | E30: =IF(B30="","",IFERROR(INDEX(Base_Gestran!$C$2:$C$5481,MATCH(B30,Base_Gestran!$A$2:$A$5481,0)),"NÃO CADASTRADO")) -> ALMOXARIFADO 1- MANUTENCAO TRANSPORTE | F30: ESTOQUE ZERADO | G30: =IF(B30="","",SUMIFS(Base_Gestran!$E$2:$E$5481,Base_Gestran!$A$2:$A$5481,B30,Base_Gestran!$C$2:$C$5481,E30)) -> 1 | H30: FRIGOKING | I30: PENDENTE | L30: =IF(B30="","",B30&"|"&TEXT(A30,"0")) -> TANQUE DE LIQUIDO SA1 AC/AE |46282
A31: 46282 | B31: PASTILHA SANITÁRIA | C31: =IF(B31="","",IF(SUMIFS(Controle_Estoque!$H$8:$H$150,Controle_Estoque!$A$8:$A$150,B31,Controle_Estoque!$B$8:$B$150,E31)=0,"",SUMIFS(Controle_Estoque!$H$8:$H$150,Controle_Estoque!$A$8:$A$150,B31,Controle_Estoque!$B$8:$B$150,E31))) | E31: =IF(B31="","",IFERROR(INDEX(Base_Gestran!$C$2:$C$5481,MATCH(B31,Base_Gestran!$A$2:$A$5481,0)),"NÃO CADASTRADO")) -> ALMOXARIFADO 5- LIMPEZA | F31: ESTOQUE BAIXO | G31: =IF(B31="","",SUMIFS(Base_Gestran!$E$2:$E$5481,Base_Gestran!$A$2:$A$5481,B31,Base_Gestran!$C$2:$C$5481,E31)) -> 129 | H31: =IF(B31="","",IFERROR(INDEX(Historico_Entradas!$D$2:$D$2009,MATCH(B31&"|"&TEXT(SUMPRODUCT(MAX((Historico_Entradas!$G$2:$G$2009=B31)*Historico_Entradas!$A$2:$A$2009)),"0"),Historico_Entradas!$L$2:$L$2009,0)),"")) | I31: PENDENTE | L31: =IF(B31="","",B31&"|"&TEXT(A31,"0")) -> PASTILHA SANITÁRIA|46282
A32: 46282 | B32: DESENTUPIDOR DE VASO COM CABO | C32: =IF(B32="","",IF(SUMIFS(Controle_Estoque!$H$8:$H$150,Controle_Estoque!$A$8:$A$150,B32,Controle_Estoque!$B$8:$B$150,E32)=0,"",SUMIFS(Controle_Estoque!$H$8:$H$150,Controle_Estoque!$A$8:$A$150,B32,Controle_Estoque!$B$8:$B$150,E32))) -> 33 | E32: =IF(B32="","",IFERROR(INDEX(Base_Gestran!$C$2:$C$5481,MATCH(B32,Base_Gestran!$A$2:$A$5481,0)),"NÃO CADASTRADO")) -> ALMOXARIFADO | F32: ESTOQUE BAIXO | G32: =IF(B32="","",SUMIFS(Base_Gestran!$E$2:$E$5481,Base_Gestran!$A$2:$A$5481,B32,Base_Gestran!$C$2:$C$5481,E32)) -> 1 | H32: =IF(B32="","",IFERROR(INDEX(Historico_Entradas!$D$2:$D$2009,MATCH(B32&"|"&TEXT(SUMPRODUCT(MAX((Historico_Entradas!$G$2:$G$2009=B32)*Historico_Entradas!$A$2:$A$2009)),"0"),Historico_Entradas!$L$2:$L$2009,0)),"")) | I32: PENDENTE | L32: =IF(B32="","",B32&"|"&TEXT(A32,"0")) -> DESENTUPIDOR DE VASO COM CABO|46282
A33: 46287 | B33: CAMISA G AZUL | C33: =IF(B33="","",IF(SUMIFS(Controle_Estoque!$H$8:$H$150,Controle_Estoque!$A$8:$A$150,B33,Controle_Estoque!$B$8:$B$150,E33)=0,"",SUMIFS(Controle_Estoque!$H$8:$H$150,Controle_Estoque!$A$8:$A$150,B33,Controle_Estoque!$B$8:$B$150,E33))) | E33: =IF(B33="","",IFERROR(INDEX(Base_Gestran!$C$2:$C$5481,MATCH(B33,Base_Gestran!$A$2:$A$5481,0)),"NÃO CADASTRADO")) -> NÃO CADASTRADO | F33: ESTOQUE ZERADO | G33: =IF(B33="","",SUMIFS(Base_Gestran!$E$2:$E$5481,Base_Gestran!$A$2:$A$5481,B33,Base_Gestran!$C$2:$C$5481,E33)) -> 0 | H33: =IF(B33="","",IFERROR(INDEX(Historico_Entradas!$D$2:$D$2009,MATCH(B33&"|"&TEXT(SUMPRODUCT(MAX((Historico_Entradas!$G$2:$G$2009=B33)*Historico_Entradas!$A$2:$A$2009)),"0"),Historico_Entradas!$L$2:$L$2009,0)),"")) | I33: PENDENTE | L33: =IF(B33="","",B33&"|"&TEXT(A33,"0")) -> CAMISA G AZUL|46287
A34: 46287 | B34: CAMISA G VERMELHA | C34: =IF(B34="","",IF(SUMIFS(Controle_Estoque!$H$8:$H$150,Controle_Estoque!$A$8:$A$150,B34,Controle_Estoque!$B$8:$B$150,E34)=0,"",SUMIFS(Controle_Estoque!$H$8:$H$150,Controle_Estoque!$A$8:$A$150,B34,Controle_Estoque!$B$8:$B$150,E34))) | E34: =IF(B34="","",IFERROR(INDEX(Base_Gestran!$C$2:$C$5481,MATCH(B34,Base_Gestran!$A$2:$A$5481,0)),"NÃO CADASTRADO")) -> NÃO CADASTRADO | F34: ESTOQUE ZERADO | G34: =IF(B34="","",SUMIFS(Base_Gestran!$E$2:$E$5481,Base_Gestran!$A$2:$A$5481,B34,Base_Gestran!$C$2:$C$5481,E34)) -> 0 | H34: =IF(B34="","",IFERROR(INDEX(Historico_Entradas!$D$2:$D$2009,MATCH(B34&"|"&TEXT(SUMPRODUCT(MAX((Historico_Entradas!$G$2:$G$2009=B34)*Historico_Entradas!$A$2:$A$2009)),"0"),Historico_Entradas!$L$2:$L$2009,0)),"")) | I34: PENDENTE | L34: =IF(B34="","",B34&"|"&TEXT(A34,"0")) -> CAMISA G VERMELHA|46287
A35: 46287 | B35: CONTROLADOR SA1 | C35: =IF(B35="","",IF(SUMIFS(Controle_Estoque!$H$8:$H$150,Controle_Estoque!$A$8:$A$150,B35,Controle_Estoque!$B$8:$B$150,E35)=0,"",SUMIFS(Controle_Estoque!$H$8:$H$150,Controle_Estoque!$A$8:$A$150,B35,Controle_Estoque!$B$8:$B$150,E35))) | E35: =IF(B35="","",IFERROR(INDEX(Base_Gestran!$C$2:$C$5481,MATCH(B35,Base_Gestran!$A$2:$A$5481,0)),"NÃO CADASTRADO")) -> NÃO CADASTRADO | F35: ESTOQUE ZERADO | G35: =IF(B35="","",SUMIFS(Base_Gestran!$E$2:$E$5481,Base_Gestran!$A$2:$A$5481,B35,Base_Gestran!$C$2:$C$5481,E35)) -> 0 | H35: =IF(B35="","",IFERROR(INDEX(Historico_Entradas!$D$2:$D$2009,MATCH(B35&"|"&TEXT(SUMPRODUCT(MAX((Historico_Entradas!$G$2:$G$2009=B35)*Historico_Entradas!$A$2:$A$2009)),"0"),Historico_Entradas!$L$2:$L$2009,0)),"")) | I35: SOLICITADO | L35: =IF(B35="","",B35&"|"&TEXT(A35,"0")) -> CONTROLADOR SA1|46287
A36: 46287 | B36: CHICOTE SA1 | C36: =IF(B36="","",IF(SUMIFS(Controle_Estoque!$H$8:$H$150,Controle_Estoque!$A$8:$A$150,B36,Controle_Estoque!$B$8:$B$150,E36)=0,"",SUMIFS(Controle_Estoque!$H$8:$H$150,Controle_Estoque!$A$8:$A$150,B36,Controle_Estoque!$B$8:$B$150,E36))) | E36: =IF(B36="","",IFERROR(INDEX(Base_Gestran!$C$2:$C$5481,MATCH(B36,Base_Gestran!$A$2:$A$5481,0)),"NÃO CADASTRADO")) -> NÃO CADASTRADO | F36: ESTOQUE ZERADO | G36: =IF(B36="","",SUMIFS(Base_Gestran!$E$2:$E$5481,Base_Gestran!$A$2:$A$5481,B36,Base_Gestran!$C$2:$C$5481,E36)) -> 0 | H36: =IF(B36="","",IFERROR(INDEX(Historico_Entradas!$D$2:$D$2009,MATCH(B36&"|"&TEXT(SUMPRODUCT(MAX((Historico_Entradas!$G$2:$G$2009=B36)*Historico_Entradas!$A$2:$A$2009)),"0"),Historico_Entradas!$L$2:$L$2009,0)),"")) | I36: SOLICITADO | L36: =IF(B36="","",B36&"|"&TEXT(A36,"0")) -> CHICOTE SA1|46287
A37: 46287 | B37: filtro de óleo do motor (accelo 1016 e vw 11.180) | C37: =IF(B37="","",IF(SUMIFS(Controle_Estoque!$H$8:$H$150,Controle_Estoque!$A$8:$A$150,B37,Controle_Estoque!$B$8:$B$150,E37)=0,"",SUMIFS(Controle_Estoque!$H$8:$H$150,Controle_Estoque!$A$8:$A$150,B37,Controle_Estoque!$B$8:$B$150,E37))) | E37: =IF(B37="","",IFERROR(INDEX(Base_Gestran!$C$2:$C$5481,MATCH(B37,Base_Gestran!$A$2:$A$5481,0)),"NÃO CADASTRADO")) -> NÃO CADASTRADO | F37: ESTOQUE ZERADO | G37: =IF(B37="","",SUMIFS(Base_Gestran!$E$2:$E$5481,Base_Gestran!$A$2:$A$5481,B37,Base_Gestran!$C$2:$C$5481,E37)) -> 0 | H37: =IF(B37="","",IFERROR(INDEX(Historico_Entradas!$D$2:$D$2009,MATCH(B37&"|"&TEXT(SUMPRODUCT(MAX((Historico_Entradas!$G$2:$G$2009=B37)*Historico_Entradas!$A$2:$A$2009)),"0"),Historico_Entradas!$L$2:$L$2009,0)),"")) | I37: PENDENTE | L37: =IF(B37="","",B37&"|"&TEXT(A37,"0")) -> filtro de óleo do motor (accelo 1016 e vw 11.180)|46287
A38: 46287 | B38: filtro racor e refil do racor (accelo 1016 e vw 11.180) | C38: =IF(B38="","",IF(SUMIFS(Controle_Estoque!$H$8:$H$150,Controle_Estoque!$A$8:$A$150,B38,Controle_Estoque!$B$8:$B$150,E38)=0,"",SUMIFS(Controle_Estoque!$H$8:$H$150,Controle_Estoque!$A$8:$A$150,B38,Controle_Estoque!$B$8:$B$150,E38))) | E38: =IF(B38="","",IFERROR(INDEX(Base_Gestran!$C$2:$C$5481,MATCH(B38,Base_Gestran!$A$2:$A$5481,0)),"NÃO CADASTRADO")) -> NÃO CADASTRADO | F38: ESTOQUE ZERADO | G38: =IF(B38="","",SUMIFS(Base_Gestran!$E$2:$E$5481,Base_Gestran!$A$2:$A$5481,B38,Base_Gestran!$C$2:$C$5481,E38)) -> 0 | H38: =IF(B38="","",IFERROR(INDEX(Historico_Entradas!$D$2:$D$2009,MATCH(B38&"|"&TEXT(SUMPRODUCT(MAX((Historico_Entradas!$G$2:$G$2009=B38)*Historico_Entradas!$A$2:$A$2009)),"0"),Historico_Entradas!$L$2:$L$2009,0)),"")) | I38: PENDENTE | L38: =IF(B38="","",B38&"|"&TEXT(A38,"0")) -> filtro racor e refil do racor (accelo 1016 e vw 11.180)|46287
A39: 46287 | B39: filtro de ar (accelo 1016 e vw 11.180) | C39: =IF(B39="","",IF(SUMIFS(Controle_Estoque!$H$8:$H$150,Controle_Estoque!$A$8:$A$150,B39,Controle_Estoque!$B$8:$B$150,E39)=0,"",SUMIFS(Controle_Estoque!$H$8:$H$150,Controle_Estoque!$A$8:$A$150,B39,Controle_Estoque!$B$8:$B$150,E39))) | E39: =IF(B39="","",IFERROR(INDEX(Base_Gestran!$C$2:$C$5481,MATCH(B39,Base_Gestran!$A$2:$A$5481,0)),"NÃO CADASTRADO")) -> NÃO CADASTRADO | F39: ESTOQUE ZERADO | G39: =IF(B39="","",SUMIFS(Base_Gestran!$E$2:$E$5481,Base_Gestran!$A$2:$A$5481,B39,Base_Gestran!$C$2:$C$5481,E39)) -> 0 | H39: =IF(B39="","",IFERROR(INDEX(Historico_Entradas!$D$2:$D$2009,MATCH(B39&"|"&TEXT(SUMPRODUCT(MAX((Historico_Entradas!$G$2:$G$2009=B39)*Historico_Entradas!$A$2:$A$2009)),"0"),Historico_Entradas!$L$2:$L$2009,0)),"")) | I39: PENDENTE | L39: =IF(B39="","",B39&"|"&TEXT(A39,"0")) -> filtro de ar (accelo 1016 e vw 11.180)|46287
A40: 46287 | B40: filtro de combustível (accelo 1016 e vw 11.180) | C40: =IF(B40="","",IF(SUMIFS(Controle_Estoque!$H$8:$H$150,Controle_Estoque!$A$8:$A$150,B40,Controle_Estoque!$B$8:$B$150,E40)=0,"",SUMIFS(Controle_Estoque!$H$8:$H$150,Controle_Estoque!$A$8:$A$150,B40,Controle_Estoque!$B$8:$B$150,E40))) | E40: =IF(B40="","",IFERROR(INDEX(Base_Gestran!$C$2:$C$5481,MATCH(B40,Base_Gestran!$A$2:$A$5481,0)),"NÃO CADASTRADO")) -> NÃO CADASTRADO | F40: ESTOQUE ZERADO | G40: =IF(B40="","",SUMIFS(Base_Gestran!$E$2:$E$5481,Base_Gestran!$A$2:$A$5481,B40,Base_Gestran!$C$2:$C$5481,E40)) -> 0 | H40: =IF(B40="","",IFERROR(INDEX(Historico_Entradas!$D$2:$D$2009,MATCH(B40&"|"&TEXT(SUMPRODUCT(MAX((Historico_Entradas!$G$2:$G$2009=B40)*Historico_Entradas!$A$2:$A$2009)),"0"),Historico_Entradas!$L$2:$L$2009,0)),"")) | I40: PENDENTE | L40: =IF(B40="","",B40&"|"&TEXT(A40,"0")) -> filtro de combustível (accelo 1016 e vw 11.180)|46287
A41: 46287 | B41: refletor 50 | C41: =IF(B41="","",IF(SUMIFS(Controle_Estoque!$H$8:$H$150,Controle_Estoque!$A$8:$A$150,B41,Controle_Estoque!$B$8:$B$150,E41)=0,"",SUMIFS(Controle_Estoque!$H$8:$H$150,Controle_Estoque!$A$8:$A$150,B41,Controle_Estoque!$B$8:$B$150,E41))) | E41: =IF(B41="","",IFERROR(INDEX(Base_Gestran!$C$2:$C$5481,MATCH(B41,Base_Gestran!$A$2:$A$5481,0)),"NÃO CADASTRADO")) -> NÃO CADASTRADO | F41: ESTOQUE ZERADO | G41: =IF(B41="","",SUMIFS(Base_Gestran!$E$2:$E$5481,Base_Gestran!$A$2:$A$5481,B41,Base_Gestran!$C$2:$C$5481,E41)) -> 0 | H41: =IF(B41="","",IFERROR(INDEX(Historico_Entradas!$D$2:$D$2009,MATCH(B41&"|"&TEXT(SUMPRODUCT(MAX((Historico_Entradas!$G$2:$G$2009=B41)*Historico_Entradas!$A$2:$A$2009)),"0"),Historico_Entradas!$L$2:$L$2009,0)),"")) | I41: PENDENTE | L41: =IF(B41="","",B41&"|"&TEXT(A41,"0")) -> refletor 50|46287
A42: 46287 | B42: galha de florescente completa 40 | C42: =IF(B42="","",IF(SUMIFS(Controle_Estoque!$H$8:$H$150,Controle_Estoque!$A$8:$A$150,B42,Controle_Estoque!$B$8:$B$150,E42)=0,"",SUMIFS(Controle_Estoque!$H$8:$H$150,Controle_Estoque!$A$8:$A$150,B42,Controle_Estoque!$B$8:$B$150,E42))) | E42: =IF(B42="","",IFERROR(INDEX(Base_Gestran!$C$2:$C$5481,MATCH(B42,Base_Gestran!$A$2:$A$5481,0)),"NÃO CADASTRADO")) -> NÃO CADASTRADO | F42: ESTOQUE ZERADO | G42: =IF(B42="","",SUMIFS(Base_Gestran!$E$2:$E$5481,Base_Gestran!$A$2:$A$5481,B42,Base_Gestran!$C$2:$C$5481,E42)) -> 0 | H42: =IF(B42="","",IFERROR(INDEX(Historico_Entradas!$D$2:$D$2009,MATCH(B42&"|"&TEXT(SUMPRODUCT(MAX((Historico_Entradas!$G$2:$G$2009=B42)*Historico_Entradas!$A$2:$A$2009)),"0"),Historico_Entradas!$L$2:$L$2009,0)),"")) | I42: PENDENTE | L42: =IF(B42="","",B42&"|"&TEXT(A42,"0")) -> galha de florescente completa 40|46287
C43: =IF(B43="","",IF(SUMIFS(Controle_Estoque!$H$8:$H$150,Controle_Estoque!$A$8:$A$150,B43,Controle_Estoque!$B$8:$B$150,E43)=0,"",SUMIFS(Controle_Estoque!$H$8:$H$150,Controle_Estoque!$A$8:$A$150,B43,Controle_Estoque!$B$8:$B$150,E43))) | E43: =IF(B43="","",IFERROR(INDEX(Base_Gestran!$C$2:$C$5481,MATCH(B43,Base_Gestran!$A$2:$A$5481,0)),"NÃO CADASTRADO")) | G43: =IF(B43="","",SUMIFS(Base_Gestran!$E$2:$E$5481,Base_Gestran!$A$2:$A$5481,B43,Base_Gestran!$C$2:$C$5481,E43)) | H43: =IF(B43="","",IFERROR(INDEX(Historico_Entradas!$D$2:$D$2009,MATCH(B43&"|"&TEXT(SUMPRODUCT(MAX((Historico_Entradas!$G$2:$G$2009=B43)*Historico_Entradas!$A$2:$A$2009)),"0"),Historico_Entradas!$L$2:$L$2009,0)),"")) | L43: =IF(B43="","",B43&"|"&TEXT(A43,"0"))
C44: =IF(B44="","",IF(SUMIFS(Controle_Estoque!$H$8:$H$150,Controle_Estoque!$A$8:$A$150,B44,Controle_Estoque!$B$8:$B$150,E44)=0,"",SUMIFS(Controle_Estoque!$H$8:$H$150,Controle_Estoque!$A$8:$A$150,B44,Controle_Estoque!$B$8:$B$150,E44))) | E44: =IF(B44="","",IFERROR(INDEX(Base_Gestran!$C$2:$C$5481,MATCH(B44,Base_Gestran!$A$2:$A$5481,0)),"NÃO CADASTRADO")) | G44: =IF(B44="","",SUMIFS(Base_Gestran!$E$2:$E$5481,Base_Gestran!$A$2:$A$5481,B44,Base_Gestran!$C$2:$C$5481,E44)) | H44: =IF(B44="","",IFERROR(INDEX(Historico_Entradas!$D$2:$D$2009,MATCH(B44&"|"&TEXT(SUMPRODUCT(MAX((Historico_Entradas!$G$2:$G$2009=B44)*Historico_Entradas!$A$2:$A$2009)),"0"),Historico_Entradas!$L$2:$L$2009,0)),"")) | L44: =IF(B44="","",B44&"|"&TEXT(A44,"0"))
C45: =IF(B45="","",IF(SUMIFS(Controle_Estoque!$H$8:$H$150,Controle_Estoque!$A$8:$A$150,B45,Controle_Estoque!$B$8:$B$150,E45)=0,"",SUMIFS(Controle_Estoque!$H$8:$H$150,Controle_Estoque!$A$8:$A$150,B45,Controle_Estoque!$B$8:$B$150,E45))) | E45: =IF(B45="","",IFERROR(INDEX(Base_Gestran!$C$2:$C$5481,MATCH(B45,Base_Gestran!$A$2:$A$5481,0)),"NÃO CADASTRADO")) | G45: =IF(B45="","",SUMIFS(Base_Gestran!$E$2:$E$5481,Base_Gestran!$A$2:$A$5481,B45,Base_Gestran!$C$2:$C$5481,E45)) | H45: =IF(B45="","",IFERROR(INDEX(Historico_Entradas!$D$2:$D$2009,MATCH(B45&"|"&TEXT(SUMPRODUCT(MAX((Historico_Entradas!$G$2:$G$2009=B45)*Historico_Entradas!$A$2:$A$2009)),"0"),Historico_Entradas!$L$2:$L$2009,0)),"")) | L45: =IF(B45="","",B45&"|"&TEXT(A45,"0")) | M45: =IF(B45="","",IF(SUMIFS(Base_Gestran!$H$2:$H$5481,Base_Gestran!$A$2:$A$5481,B45,Base_Gestran!$C$2:$C$5481,E45)=0,"",SUMIFS(Base_Gestran!$H$2:$H$5481,Base_Gestran!$A$2:$A$5481,B45,Base_Gestran!$C$2:$C$5481,E45)))
C46: =IF(B46="","",IF(SUMIFS(Controle_Estoque!$H$8:$H$150,Controle_Estoque!$A$8:$A$150,B46,Controle_Estoque!$B$8:$B$150,E46)=0,"",SUMIFS(Controle_Estoque!$H$8:$H$150,Controle_Estoque!$A$8:$A$150,B46,Controle_Estoque!$B$8:$B$150,E46))) | E46: =IF(B46="","",IFERROR(INDEX(Base_Gestran!$C$2:$C$5481,MATCH(B46,Base_Gestran!$A$2:$A$5481,0)),"NÃO CADASTRADO")) | G46: =IF(B46="","",SUMIFS(Base_Gestran!$E$2:$E$5481,Base_Gestran!$A$2:$A$5481,B46,Base_Gestran!$C$2:$C$5481,E46)) | H46: =IF(B46="","",IFERROR(INDEX(Historico_Entradas!$D$2:$D$2009,MATCH(B46&"|"&TEXT(SUMPRODUCT(MAX((Historico_Entradas!$G$2:$G$2009=B46)*Historico_Entradas!$A$2:$A$2009)),"0"),Historico_Entradas!$L$2:$L$2009,0)),"")) | L46: =IF(B46="","",B46&"|"&TEXT(A46,"0")) | M46: =IF(B46="","",IF(SUMIFS(Base_Gestran!$H$2:$H$5481,Base_Gestran!$A$2:$A$5481,B46,Base_Gestran!$C$2:$C$5481,E46)=0,"",SUMIFS(Base_Gestran!$H$2:$H$5481,Base_Gestran!$A$2:$A$5481,B46,Base_Gestran!$C$2:$C$5481,E46)))
C47: =IF(B47="","",IF(SUMIFS(Controle_Estoque!$H$8:$H$150,Controle_Estoque!$A$8:$A$150,B47,Controle_Estoque!$B$8:$B$150,E47)=0,"",SUMIFS(Controle_Estoque!$H$8:$H$150,Controle_Estoque!$A$8:$A$150,B47,Controle_Estoque!$B$8:$B$150,E47))) | E47: =IF(B47="","",IFERROR(INDEX(Base_Gestran!$C$2:$C$5481,MATCH(B47,Base_Gestran!$A$2:$A$5481,0)),"NÃO CADASTRADO")) | G47: =IF(B47="","",SUMIFS(Base_Gestran!$E$2:$E$5481,Base_Gestran!$A$2:$A$5481,B47,Base_Gestran!$C$2:$C$5481,E47)) | H47: =IF(B47="","",IFERROR(INDEX(Historico_Entradas!$D$2:$D$2009,MATCH(B47&"|"&TEXT(SUMPRODUCT(MAX((Historico_Entradas!$G$2:$G$2009=B47)*Historico_Entradas!$A$2:$A$2009)),"0"),Historico_Entradas!$L$2:$L$2009,0)),"")) | L47: =IF(B47="","",B47&"|"&TEXT(A47,"0")) | M47: =IF(B47="","",IF(SUMIFS(Base_Gestran!$H$2:$H$5481,Base_Gestran!$A$2:$A$5481,B47,Base_Gestran!$C$2:$C$5481,E47)=0,"",SUMIFS(Base_Gestran!$H$2:$H$5481,Base_Gestran!$A$2:$A$5481,B47,Base_Gestran!$C$2:$C$5481,E47)))
C48: =IF(B48="","",IF(SUMIFS(Controle_Estoque!$H$8:$H$150,Controle_Estoque!$A$8:$A$150,B48,Controle_Estoque!$B$8:$B$150,E48)=0,"",SUMIFS(Controle_Estoque!$H$8:$H$150,Controle_Estoque!$A$8:$A$150,B48,Controle_Estoque!$B$8:$B$150,E48))) | E48: =IF(B48="","",IFERROR(INDEX(Base_Gestran!$C$2:$C$5481,MATCH(B48,Base_Gestran!$A$2:$A$5481,0)),"NÃO CADASTRADO")) | G48: =IF(B48="","",SUMIFS(Base_Gestran!$E$2:$E$5481,Base_Gestran!$A$2:$A$5481,B48,Base_Gestran!$C$2:$C$5481,E48)) | H48: =IF(B48="","",IFERROR(INDEX(Historico_Entradas!$D$2:$D$2009,MATCH(B48&"|"&TEXT(SUMPRODUCT(MAX((Historico_Entradas!$G$2:$G$2009=B48)*Historico_Entradas!$A$2:$A$2009)),"0"),Historico_Entradas!$L$2:$L$2009,0)),"")) | L48: =IF(B48="","",B48&"|"&TEXT(A48,"0")) | M48: =IF(B48="","",IF(SUMIFS(Base_Gestran!$H$2:$H$5481,Base_Gestran!$A$2:$A$5481,B48,Base_Gestran!$C$2:$C$5481,E48)=0,"",SUMIFS(Base_Gestran!$H$2:$H$5481,Base_Gestran!$A$2:$A$5481,B48,Base_Gestran!$C$2:$C$5481,E48)))
C49: =IF(B49="","",IF(SUMIFS(Controle_Estoque!$H$8:$H$150,Controle_Estoque!$A$8:$A$150,B49,Controle_Estoque!$B$8:$B$150,E49)=0,"",SUMIFS(Controle_Estoque!$H$8:$H$150,Controle_Estoque!$A$8:$A$150,B49,Controle_Estoque!$B$8:$B$150,E49))) | E49: =IF(B49="","",IFERROR(INDEX(Base_Gestran!$C$2:$C$5481,MATCH(B49,Base_Gestran!$A$2:$A$5481,0)),"NÃO CADASTRADO")) | G49: =IF(B49="","",SUMIFS(Base_Gestran!$E$2:$E$5481,Base_Gestran!$A$2:$A$5481,B49,Base_Gestran!$C$2:$C$5481,E49)) | H49: =IF(B49="","",IFERROR(INDEX(Historico_Entradas!$D$2:$D$2009,MATCH(B49&"|"&TEXT(SUMPRODUCT(MAX((Historico_Entradas!$G$2:$G$2009=B49)*Historico_Entradas!$A$2:$A$2009)),"0"),Historico_Entradas!$L$2:$L$2009,0)),"")) | L49: =IF(B49="","",B49&"|"&TEXT(A49,"0")) | M49: =IF(B49="","",IF(SUMIFS(Base_Gestran!$H$2:$H$5481,Base_Gestran!$A$2:$A$5481,B49,Base_Gestran!$C$2:$C$5481,E49)=0,"",SUMIFS(Base_Gestran!$H$2:$H$5481,Base_Gestran!$A$2:$A$5481,B49,Base_Gestran!$C$2:$C$5481,E49)))
C50: =IF(B50="","",IF(SUMIFS(Controle_Estoque!$H$8:$H$150,Controle_Estoque!$A$8:$A$150,B50,Controle_Estoque!$B$8:$B$150,E50)=0,"",SUMIFS(Controle_Estoque!$H$8:$H$150,Controle_Estoque!$A$8:$A$150,B50,Controle_Estoque!$B$8:$B$150,E50))) | E50: =IF(B50="","",IFERROR(INDEX(Base_Gestran!$C$2:$C$5481,MATCH(B50,Base_Gestran!$A$2:$A$5481,0)),"NÃO CADASTRADO")) | G50: =IF(B50="","",SUMIFS(Base_Gestran!$E$2:$E$5481,Base_Gestran!$A$2:$A$5481,B50,Base_Gestran!$C$2:$C$5481,E50)) | H50: =IF(B50="","",IFERROR(INDEX(Historico_Entradas!$D$2:$D$2009,MATCH(B50&"|"&TEXT(SUMPRODUCT(MAX((Historico_Entradas!$G$2:$G$2009=B50)*Historico_Entradas!$A$2:$A$2009)),"0"),Historico_Entradas!$L$2:$L$2009,0)),"")) | L50: =IF(B50="","",B50&"|"&TEXT(A50,"0")) | M50: =IF(B50="","",IF(SUMIFS(Base_Gestran!$H$2:$H$5481,Base_Gestran!$A$2:$A$5481,B50,Base_Gestran!$C$2:$C$5481,E50)=0,"",SUMIFS(Base_Gestran!$H$2:$H$5481,Base_Gestran!$A$2:$A$5481,B50,Base_Gestran!$C$2:$C$5481,E50)))
C51: =IF(B51="","",IF(SUMIFS(Controle_Estoque!$H$8:$H$150,Controle_Estoque!$A$8:$A$150,B51,Controle_Estoque!$B$8:$B$150,E51)=0,"",SUMIFS(Controle_Estoque!$H$8:$H$150,Controle_Estoque!$A$8:$A$150,B51,Controle_Estoque!$B$8:$B$150,E51))) | E51: =IF(B51="","",IFERROR(INDEX(Base_Gestran!$C$2:$C$5481,MATCH(B51,Base_Gestran!$A$2:$A$5481,0)),"NÃO CADASTRADO")) | G51: =IF(B51="","",SUMIFS(Base_Gestran!$E$2:$E$5481,Base_Gestran!$A$2:$A$5481,B51,Base_Gestran!$C$2:$C$5481,E51)) | H51: =IF(B51="","",IFERROR(INDEX(Historico_Entradas!$D$2:$D$2009,MATCH(B51&"|"&TEXT(SUMPRODUCT(MAX((Historico_Entradas!$G$2:$G$2009=B51)*Historico_Entradas!$A$2:$A$2009)),"0"),Historico_Entradas!$L$2:$L$2009,0)),"")) | L51: =IF(B51="","",B51&"|"&TEXT(A51,"0")) | M51: =IF(B51="","",IF(SUMIFS(Base_Gestran!$H$2:$H$5481,Base_Gestran!$A$2:$A$5481,B51,Base_Gestran!$C$2:$C$5481,E51)=0,"",SUMIFS(Base_Gestran!$H$2:$H$5481,Base_Gestran!$A$2:$A$5481,B51,Base_Gestran!$C$2:$C$5481,E51)))
C52: =IF(B52="","",IF(SUMIFS(Controle_Estoque!$H$8:$H$150,Controle_Estoque!$A$8:$A$150,B52,Controle_Estoque!$B$8:$B$150,E52)=0,"",SUMIFS(Controle_Estoque!$H$8:$H$150,Controle_Estoque!$A$8:$A$150,B52,Controle_Estoque!$B$8:$B$150,E52))) | E52: =IF(B52="","",IFERROR(INDEX(Base_Gestran!$C$2:$C$5481,MATCH(B52,Base_Gestran!$A$2:$A$5481,0)),"NÃO CADASTRADO")) | G52: =IF(B52="","",SUMIFS(Base_Gestran!$E$2:$E$5481,Base_Gestran!$A$2:$A$5481,B52,Base_Gestran!$C$2:$C$5481,E52)) | H52: =IF(B52="","",IFERROR(INDEX(Historico_Entradas!$D$2:$D$2009,MATCH(B52&"|"&TEXT(SUMPRODUCT(MAX((Historico_Entradas!$G$2:$G$2009=B52)*Historico_Entradas!$A$2:$A$2009)),"0"),Historico_Entradas!$L$2:$L$2009,0)),"")) | L52: =IF(B52="","",B52&"|"&TEXT(A52,"0")) | M52: =IF(B52="","",IF(SUMIFS(Base_Gestran!$H$2:$H$5481,Base_Gestran!$A$2:$A$5481,B52,Base_Gestran!$C$2:$C$5481,E52)=0,"",SUMIFS(Base_Gestran!$H$2:$H$5481,Base_Gestran!$A$2:$A$5481,B52,Base_Gestran!$C$2:$C$5481,E52)))
C53: =IF(B53="","",IF(SUMIFS(Controle_Estoque!$H$8:$H$150,Controle_Estoque!$A$8:$A$150,B53,Controle_Estoque!$B$8:$B$150,E53)=0,"",SUMIFS(Controle_Estoque!$H$8:$H$150,Controle_Estoque!$A$8:$A$150,B53,Controle_Estoque!$B$8:$B$150,E53))) | E53: =IF(B53="","",IFERROR(INDEX(Base_Gestran!$C$2:$C$5481,MATCH(B53,Base_Gestran!$A$2:$A$5481,0)),"NÃO CADASTRADO")) | G53: =IF(B53="","",SUMIFS(Base_Gestran!$E$2:$E$5481,Base_Gestran!$A$2:$A$5481,B53,Base_Gestran!$C$2:$C$5481,E53)) | H53: =IF(B53="","",IFERROR(INDEX(Historico_Entradas!$D$2:$D$2009,MATCH(B53&"|"&TEXT(SUMPRODUCT(MAX((Historico_Entradas!$G$2:$G$2009=B53)*Historico_Entradas!$A$2:$A$2009)),"0"),Historico_Entradas!$L$2:$L$2009,0)),"")) | L53: =IF(B53="","",B53&"|"&TEXT(A53,"0")) | M53: =IF(B53="","",IF(SUMIFS(Base_Gestran!$H$2:$H$5481,Base_Gestran!$A$2:$A$5481,B53,Base_Gestran!$C$2:$C$5481,E53)=0,"",SUMIFS(Base_Gestran!$H$2:$H$5481,Base_Gestran!$A$2:$A$5481,B53,Base_Gestran!$C$2:$C$5481,E53)))
C54: =IF(B54="","",IF(SUMIFS(Controle_Estoque!$H$8:$H$150,Controle_Estoque!$A$8:$A$150,B54,Controle_Estoque!$B$8:$B$150,E54)=0,"",SUMIFS(Controle_Estoque!$H$8:$H$150,Controle_Estoque!$A$8:$A$150,B54,Controle_Estoque!$B$8:$B$150,E54))) | E54: =IF(B54="","",IFERROR(INDEX(Base_Gestran!$C$2:$C$5481,MATCH(B54,Base_Gestran!$A$2:$A$5481,0)),"NÃO CADASTRADO")) | G54: =IF(B54="","",SUMIFS(Base_Gestran!$E$2:$E$5481,Base_Gestran!$A$2:$A$5481,B54,Base_Gestran!$C$2:$C$5481,E54)) | H54: =IF(B54="","",IFERROR(INDEX(Historico_Entradas!$D$2:$D$2009,MATCH(B54&"|"&TEXT(SUMPRODUCT(MAX((Historico_Entradas!$G$2:$G$2009=B54)*Historico_Entradas!$A$2:$A$2009)),"0"),Historico_Entradas!$L$2:$L$2009,0)),"")) | L54: =IF(B54="","",B54&"|"&TEXT(A54,"0")) | M54: =IF(B54="","",IF(SUMIFS(Base_Gestran!$H$2:$H$5481,Base_Gestran!$A$2:$A$5481,B54,Base_Gestran!$C$2:$C$5481,E54)=0,"",SUMIFS(Base_Gestran!$H$2:$H$5481,Base_Gestran!$A$2:$A$5481,B54,Base_Gestran!$C$2:$C$5481,E54)))
C55: =IF(B55="","",IF(SUMIFS(Controle_Estoque!$H$8:$H$150,Controle_Estoque!$A$8:$A$150,B55,Controle_Estoque!$B$8:$B$150,E55)=0,"",SUMIFS(Controle_Estoque!$H$8:$H$150,Controle_Estoque!$A$8:$A$150,B55,Controle_Estoque!$B$8:$B$150,E55))) | E55: =IF(B55="","",IFERROR(INDEX(Base_Gestran!$C$2:$C$5481,MATCH(B55,Base_Gestran!$A$2:$A$5481,0)),"NÃO CADASTRADO")) | G55: =IF(B55="","",SUMIFS(Base_Gestran!$E$2:$E$5481,Base_Gestran!$A$2:$A$5481,B55,Base_Gestran!$C$2:$C$5481,E55)) | H55: =IF(B55="","",IFERROR(INDEX(Historico_Entradas!$D$2:$D$2009,MATCH(B55&"|"&TEXT(SUMPRODUCT(MAX((Historico_Entradas!$G$2:$G$2009=B55)*Historico_Entradas!$A$2:$A$2009)),"0"),Historico_Entradas!$L$2:$L$2009,0)),"")) | L55: =IF(B55="","",B55&"|"&TEXT(A55,"0")) | M55: =IF(B55="","",IF(SUMIFS(Base_Gestran!$H$2:$H$5481,Base_Gestran!$A$2:$A$5481,B55,Base_Gestran!$C$2:$C$5481,E55)=0,"",SUMIFS(Base_Gestran!$H$2:$H$5481,Base_Gestran!$A$2:$A$5481,B55,Base_Gestran!$C$2:$C$5481,E55)))
C56: =IF(B56="","",IF(SUMIFS(Controle_Estoque!$H$8:$H$150,Controle_Estoque!$A$8:$A$150,B56,Controle_Estoque!$B$8:$B$150,E56)=0,"",SUMIFS(Controle_Estoque!$H$8:$H$150,Controle_Estoque!$A$8:$A$150,B56,Controle_Estoque!$B$8:$B$150,E56))) | E56: =IF(B56="","",IFERROR(INDEX(Base_Gestran!$C$2:$C$5481,MATCH(B56,Base_Gestran!$A$2:$A$5481,0)),"NÃO CADASTRADO")) | G56: =IF(B56="","",SUMIFS(Base_Gestran!$E$2:$E$5481,Base_Gestran!$A$2:$A$5481,B56,Base_Gestran!$C$2:$C$5481,E56)) | H56: =IF(B56="","",IFERROR(INDEX(Historico_Entradas!$D$2:$D$2009,MATCH(B56&"|"&TEXT(SUMPRODUCT(MAX((Historico_Entradas!$G$2:$G$2009=B56)*Historico_Entradas!$A$2:$A$2009)),"0"),Historico_Entradas!$L$2:$L$2009,0)),"")) | L56: =IF(B56="","",B56&"|"&TEXT(A56,"0")) | M56: =IF(B56="","",IF(SUMIFS(Base_Gestran!$H$2:$H$5481,Base_Gestran!$A$2:$A$5481,B56,Base_Gestran!$C$2:$C$5481,E56)=0,"",SUMIFS(Base_Gestran!$H$2:$H$5481,Base_Gestran!$A$2:$A$5481,B56,Base_Gestran!$C$2:$C$5481,E56)))
... C60: =IF(B60="","",IF(SUMIFS(Controle_Estoque!$H$8:$H$150,Controle_Estoque!$A$8:$A$150,B60,Controle_Estoque!$B$8:$B$150,E60)=0,"",SUMIFS(Controle_Estoque!$H$8:$H$150,Controle_Estoque!$A$8:$A$150,B60,Controle_Estoque!$B$8:$B$150,E60))) | E60: =IF(B60="","",IFERROR(INDEX(Base_Gestran!$C$2:$C$5481,MATCH(B60,Base_Gestran!$A$2:$A$5481,0)),"NÃO CADASTRADO")) | G60: =IF(B60="","",SUMIFS(Base_Gestran!$E$2:$E$5481,Base_Gestran!$A$2:$A$5481,B60,Base_Gestran!$C$2:$C$5481,E60)) | H60: =IF(B60="","",IFERROR(INDEX(Historico_Entradas!$D$2:$D$2009,MATCH(B60&"|"&TEXT(SUMPRODUCT(MAX((Historico_Entradas!$G$2:$G$2009=B60)*Historico_Entradas!$A$2:$A$2009)),"0"),Historico_Entradas!$L$2:$L$2009,0)),"")) | L60: =IF(B60="","",B60&"|"&TEXT(A60,"0")) | M60: =IF(B60="","",IF(SUMIFS(Base_Gestran!$H$2:$H$5481,Base_Gestran!$A$2:$A$5481,B60,Base_Gestran!$C$2:$C$5481,E60)=0,"",SUMIFS(Base_Gestran!$H$2:$H$5481,Base_Gestran!$A$2:$A$5481,B60,Base_Gestran!$C$2:$C$5481,E60)))

Sheet Analises_Gerais
A1: ANÁLISE GERAL DO ESTOQUE — VISÃO PARA A DIRETORIA
A2: Baseado no export do Gestran (aba Base_Gestran). Atualiza sozinho quando você colar um novo export.
A4: Total de cadastros (linhas) na base | B4: =COUNTA(Base_Gestran!A2:A5481) -> 5480
A5: Cadastros com saldo físico > 0 | B5: =COUNTIFS(Base_Gestran!E2:E5481,">0") -> 4484
A6: Cadastros com saldo ZERADO | B6: =COUNTIFS(Base_Gestran!E2:E5481,0) -> 990
A7: Cadastros com saldo NEGATIVO (erro a corrigir) | B7: =COUNTIFS(Base_Gestran!E2:E5481,"<0") -> 6
A8: % da base realmente com estoque | B8: =B5/B4 -> 0.81824818
A9: Valor total em estoque (R$) | B9: =SUM(Base_Gestran!J2:J5481) -> 5119194.7
A10: Cadastros sem NENHUM registro de saída (parados) | B10: =COUNTIFS(Base_Gestran!G2:G5481,"") -> 3461
A11: Produtos com mesmo nome cadastrado em +1 registro (possível marca/local fragmentado) | B11: =COUNTIFS(Base_Gestran!M2:M5481,">1") -> 1492
A13: TOP 20 ITENS POR VALOR PARADO EM ESTOQUE
A14: POSIÇÃO | B14: Produto | C14: Almoxarifado | D14: Saldo | E14: Valor Total em Estoque (R$)
A15: 1 | B15: =INDEX(Base_Gestran!$A$2:$A$5481,MATCH(LARGE(Base_Gestran!$N$2:$N$5481,1),Base_Gestran!$N$2:$N$5481,0)) -> SCS PLAST TR PR LISO 20 x 30 | C15: =INDEX(Base_Gestran!$C$2:$C$5481,MATCH(LARGE(Base_Gestran!$N$2:$N$5481,1),Base_Gestran!$N$2:$N$5481,0)) -> ALMOXARIFADO 7- INDUSTRIA | D15: =INDEX(Base_Gestran!$E$2:$E$5481,MATCH(LARGE(Base_Gestran!$N$2:$N$5481,1),Base_Gestran!$N$2:$N$5481,0)) -> 3813.4 | E15: =INDEX(Base_Gestran!$J$2:$J$5481,MATCH(LARGE(Base_Gestran!$N$2:$N$5481,1),Base_Gestran!$N$2:$N$5481,0)) -> 1271273.2
A16: 2 | B16: =INDEX(Base_Gestran!$A$2:$A$5481,MATCH(LARGE(Base_Gestran!$N$2:$N$5481,2),Base_Gestran!$N$2:$N$5481,0)) -> METALON GALVANIZADO 30X50X18 | C16: =INDEX(Base_Gestran!$C$2:$C$5481,MATCH(LARGE(Base_Gestran!$N$2:$N$5481,2),Base_Gestran!$N$2:$N$5481,0)) -> ALMOXARIFADO | D16: =INDEX(Base_Gestran!$E$2:$E$5481,MATCH(LARGE(Base_Gestran!$N$2:$N$5481,2),Base_Gestran!$N$2:$N$5481,0)) -> 4 | E16: =INDEX(Base_Gestran!$J$2:$J$5481,MATCH(LARGE(Base_Gestran!$N$2:$N$5481,2),Base_Gestran!$N$2:$N$5481,0)) -> 416800
A17: 3 | B17: =INDEX(Base_Gestran!$A$2:$A$5481,MATCH(LARGE(Base_Gestran!$N$2:$N$5481,3),Base_Gestran!$N$2:$N$5481,0)) -> STRETCH MANUAL 500MM X 25 MICRA X 3 | C17: =INDEX(Base_Gestran!$C$2:$C$5481,MATCH(LARGE(Base_Gestran!$N$2:$N$5481,3),Base_Gestran!$N$2:$N$5481,0)) -> ALMOXARIFADO 9- LOGÍSTICA | D17: =INDEX(Base_Gestran!$E$2:$E$5481,MATCH(LARGE(Base_Gestran!$N$2:$N$5481,3),Base_Gestran!$N$2:$N$5481,0)) -> 12263.52 | E17: =INDEX(Base_Gestran!$J$2:$J$5481,MATCH(LARGE(Base_Gestran!$N$2:$N$5481,3),Base_Gestran!$N$2:$N$5481,0)) -> 241713.98
A18: 4 | B18: =INDEX(Base_Gestran!$A$2:$A$5481,MATCH(LARGE(Base_Gestran!$N$2:$N$5481,4),Base_Gestran!$N$2:$N$5481,0)) -> ROLAMENTO 6004ZE MARCA NACHI | C18: =INDEX(Base_Gestran!$C$2:$C$5481,MATCH(LARGE(Base_Gestran!$N$2:$N$5481,4),Base_Gestran!$N$2:$N$5481,0)) -> ALMOXARIFADO | D18: =INDEX(Base_Gestran!$E$2:$E$5481,MATCH(LARGE(Base_Gestran!$N$2:$N$5481,4),Base_Gestran!$N$2:$N$5481,0)) -> 3000 | E18: =INDEX(Base_Gestran!$J$2:$J$5481,MATCH(LARGE(Base_Gestran!$N$2:$N$5481,4),Base_Gestran!$N$2:$N$5481,0)) -> 135000
A19: 5 | B19: =INDEX(Base_Gestran!$A$2:$A$5481,MATCH(LARGE(Base_Gestran!$N$2:$N$5481,5),Base_Gestran!$N$2:$N$5481,0)) -> CX CV 25KG FUNDO | C19: =INDEX(Base_Gestran!$C$2:$C$5481,MATCH(LARGE(Base_Gestran!$N$2:$N$5481,5),Base_Gestran!$N$2:$N$5481,0)) -> ALMOXARIFADO 7- INDUSTRIA | D19: =INDEX(Base_Gestran!$E$2:$E$5481,MATCH(LARGE(Base_Gestran!$N$2:$N$5481,5),Base_Gestran!$N$2:$N$5481,0)) -> 20966 | E19: =INDEX(Base_Gestran!$J$2:$J$5481,MATCH(LARGE(Base_Gestran!$N$2:$N$5481,5),Base_Gestran!$N$2:$N$5481,0)) -> 96443.6
A20: 6 | B20: =INDEX(Base_Gestran!$A$2:$A$5481,MATCH(LARGE(Base_Gestran!$N$2:$N$5481,6),Base_Gestran!$N$2:$N$5481,0)) -> CX CV 15KG FUNDO | C20: =INDEX(Base_Gestran!$C$2:$C$5481,MATCH(LARGE(Base_Gestran!$N$2:$N$5481,6),Base_Gestran!$N$2:$N$5481,0)) -> ALMOXARIFADO 7- INDUSTRIA | D20: =INDEX(Base_Gestran!$E$2:$E$5481,MATCH(LARGE(Base_Gestran!$N$2:$N$5481,6),Base_Gestran!$N$2:$N$5481,0)) -> 15781 | E20: =INDEX(Base_Gestran!$J$2:$J$5481,MATCH(LARGE(Base_Gestran!$N$2:$N$5481,6),Base_Gestran!$N$2:$N$5481,0)) -> 64859.91
A21: 7 | B21: =INDEX(Base_Gestran!$A$2:$A$5481,MATCH(LARGE(Base_Gestran!$N$2:$N$5481,7),Base_Gestran!$N$2:$N$5481,0)) -> ETIQUETA PERSONALIZADA - INTERNO BOIBOM | C21: =INDEX(Base_Gestran!$C$2:$C$5481,MATCH(LARGE(Base_Gestran!$N$2:$N$5481,7),Base_Gestran!$N$2:$N$5481,0)) -> ALMOXARIFADO 7- INDUSTRIA | D21: =INDEX(Base_Gestran!$E$2:$E$5481,MATCH(LARGE(Base_Gestran!$N$2:$N$5481,7),Base_Gestran!$N$2:$N$5481,0)) -> 788000 | E21: =INDEX(Base_Gestran!$J$2:$J$5481,MATCH(LARGE(Base_Gestran!$N$2:$N$5481,7),Base_Gestran!$N$2:$N$5481,0)) -> 63040
A22: 8 | B22: =INDEX(Base_Gestran!$A$2:$A$5481,MATCH(LARGE(Base_Gestran!$N$2:$N$5481,8),Base_Gestran!$N$2:$N$5481,0)) -> CX CV 15KG TAMPA | C22: =INDEX(Base_Gestran!$C$2:$C$5481,MATCH(LARGE(Base_Gestran!$N$2:$N$5481,8),Base_Gestran!$N$2:$N$5481,0)) -> ALMOXARIFADO 7- INDUSTRIA | D22: =INDEX(Base_Gestran!$E$2:$E$5481,MATCH(LARGE(Base_Gestran!$N$2:$N$5481,8),Base_Gestran!$N$2:$N$5481,0)) -> 13269 | E22: =INDEX(Base_Gestran!$J$2:$J$5481,MATCH(LARGE(Base_Gestran!$N$2:$N$5481,8),Base_Gestran!$N$2:$N$5481,0)) -> 63027.75
A23: 9 | B23: =INDEX(Base_Gestran!$A$2:$A$5481,MATCH(LARGE(Base_Gestran!$N$2:$N$5481,9),Base_Gestran!$N$2:$N$5481,0)) -> CX CV 25KG TAMPA | C23: =INDEX(Base_Gestran!$C$2:$C$5481,MATCH(LARGE(Base_Gestran!$N$2:$N$5481,9),Base_Gestran!$N$2:$N$5481,0)) -> ALMOXARIFADO 7- INDUSTRIA | D23: =INDEX(Base_Gestran!$E$2:$E$5481,MATCH(LARGE(Base_Gestran!$N$2:$N$5481,9),Base_Gestran!$N$2:$N$5481,0)) -> 12961 | E23: =INDEX(Base_Gestran!$J$2:$J$5481,MATCH(LARGE(Base_Gestran!$N$2:$N$5481,9),Base_Gestran!$N$2:$N$5481,0)) -> 55732.3
A24: 10 | B24: =INDEX(Base_Gestran!$A$2:$A$5481,MATCH(LARGE(Base_Gestran!$N$2:$N$5481,10),Base_Gestran!$N$2:$N$5481,0)) -> FLUIDO REF R404A HP62 ONU 3337 | C24: =INDEX(Base_Gestran!$C$2:$C$5481,MATCH(LARGE(Base_Gestran!$N$2:$N$5481,10),Base_Gestran!$N$2:$N$5481,0)) -> ALMOXARIFADO 0- GERAL | D24: =INDEX(Base_Gestran!$E$2:$E$5481,MATCH(LARGE(Base_Gestran!$N$2:$N$5481,10),Base_Gestran!$N$2:$N$5481,0)) -> 501.4 | E24: =INDEX(Base_Gestran!$J$2:$J$5481,MATCH(LARGE(Base_Gestran!$N$2:$N$5481,10),Base_Gestran!$N$2:$N$5481,0)) -> 42027.348
A25: 11 | B25: =INDEX(Base_Gestran!$A$2:$A$5481,MATCH(LARGE(Base_Gestran!$N$2:$N$5481,11),Base_Gestran!$N$2:$N$5481,0)) -> FLUIDO REF R404A HP62 ONU 3337 | C25: =INDEX(Base_Gestran!$C$2:$C$5481,MATCH(LARGE(Base_Gestran!$N$2:$N$5481,11),Base_Gestran!$N$2:$N$5481,0)) -> ALMOXARIFADO 1- MANUTENCAO TRANSPORTE | D25: =INDEX(Base_Gestran!$E$2:$E$5481,MATCH(LARGE(Base_Gestran!$N$2:$N$5481,11),Base_Gestran!$N$2:$N$5481,0)) -> 468.3 | E25: =INDEX(Base_Gestran!$J$2:$J$5481,MATCH(LARGE(Base_Gestran!$N$2:$N$5481,11),Base_Gestran!$N$2:$N$5481,0)) -> 39529.203
A26: 12 | B26: =INDEX(Base_Gestran!$A$2:$A$5481,MATCH(LARGE(Base_Gestran!$N$2:$N$5481,12),Base_Gestran!$N$2:$N$5481,0)) -> PAPEL TOALHA BOBINA 6X20X200 | C26: =INDEX(Base_Gestran!$C$2:$C$5481,MATCH(LARGE(Base_Gestran!$N$2:$N$5481,12),Base_Gestran!$N$2:$N$5481,0)) -> ALMOXARIFADO 5- LIMPEZA | D26: =INDEX(Base_Gestran!$E$2:$E$5481,MATCH(LARGE(Base_Gestran!$N$2:$N$5481,12),Base_Gestran!$N$2:$N$5481,0)) -> 1044 | E26: =INDEX(Base_Gestran!$J$2:$J$5481,MATCH(LARGE(Base_Gestran!$N$2:$N$5481,12),Base_Gestran!$N$2:$N$5481,0)) -> 29764.44
A27: 13 | B27: =INDEX(Base_Gestran!$A$2:$A$5481,MATCH(LARGE(Base_Gestran!$N$2:$N$5481,13),Base_Gestran!$N$2:$N$5481,0)) -> BOPP BRANCO FOSCO FASSON S 2045 90MTS ZEBRA | C27: =INDEX(Base_Gestran!$C$2:$C$5481,MATCH(LARGE(Base_Gestran!$N$2:$N$5481,13),Base_Gestran!$N$2:$N$5481,0)) -> ALMOXARIFADO 9- LOGÍSTICA | D27: =INDEX(Base_Gestran!$E$2:$E$5481,MATCH(LARGE(Base_Gestran!$N$2:$N$5481,13),Base_Gestran!$N$2:$N$5481,0)) -> 329 | E27: =INDEX(Base_Gestran!$J$2:$J$5481,MATCH(LARGE(Base_Gestran!$N$2:$N$5481,13),Base_Gestran!$N$2:$N$5481,0)) -> 29100.05
A28: 14 | B28: =INDEX(Base_Gestran!$A$2:$A$5481,MATCH(LARGE(Base_Gestran!$N$2:$N$5481,14),Base_Gestran!$N$2:$N$5481,0)) -> SCS PLAST LISO NAT 20X51 | C28: =INDEX(Base_Gestran!$C$2:$C$5481,MATCH(LARGE(Base_Gestran!$N$2:$N$5481,14),Base_Gestran!$N$2:$N$5481,0)) -> ALMOXARIFADO 7- INDUSTRIA | D28: =INDEX(Base_Gestran!$E$2:$E$5481,MATCH(LARGE(Base_Gestran!$N$2:$N$5481,14),Base_Gestran!$N$2:$N$5481,0)) -> 142.6 | E28: =INDEX(Base_Gestran!$J$2:$J$5481,MATCH(LARGE(Base_Gestran!$N$2:$N$5481,14),Base_Gestran!$N$2:$N$5481,0)) -> 25409.894
A29: 15 | B29: =INDEX(Base_Gestran!$A$2:$A$5481,MATCH(LARGE(Base_Gestran!$N$2:$N$5481,15),Base_Gestran!$N$2:$N$5481,0)) -> LAVADORA A260 N/SERIE: 30201444 | C29: =INDEX(Base_Gestran!$C$2:$C$5481,MATCH(LARGE(Base_Gestran!$N$2:$N$5481,15),Base_Gestran!$N$2:$N$5481,0)) -> ALMOXARIFADO 2- MANUTENCAO PREDIAL | D29: =INDEX(Base_Gestran!$E$2:$E$5481,MATCH(LARGE(Base_Gestran!$N$2:$N$5481,15),Base_Gestran!$N$2:$N$5481,0)) -> 1 | E29: =INDEX(Base_Gestran!$J$2:$J$5481,MATCH(LARGE(Base_Gestran!$N$2:$N$5481,15),Base_Gestran!$N$2:$N$5481,0)) -> 25000
A30: 16 | B30: =INDEX(Base_Gestran!$A$2:$A$5481,MATCH(LARGE(Base_Gestran!$N$2:$N$5481,16),Base_Gestran!$N$2:$N$5481,0)) -> OLEO M-DELVAC MODERN 15W40 SD V3 MARCA M-DELVAC | C30: =INDEX(Base_Gestran!$C$2:$C$5481,MATCH(LARGE(Base_Gestran!$N$2:$N$5481,16),Base_Gestran!$N$2:$N$5481,0)) -> ALMOXARIFADO 1- MANUTENCAO TRANSPORTE | D30: =INDEX(Base_Gestran!$E$2:$E$5481,MATCH(LARGE(Base_Gestran!$N$2:$N$5481,16),Base_Gestran!$N$2:$N$5481,0)) -> 1200 | E30: =INDEX(Base_Gestran!$J$2:$J$5481,MATCH(LARGE(Base_Gestran!$N$2:$N$5481,16),Base_Gestran!$N$2:$N$5481,0)) -> 22920
A31: 17 | B31: =INDEX(Base_Gestran!$A$2:$A$5481,MATCH(LARGE(Base_Gestran!$N$2:$N$5481,17),Base_Gestran!$N$2:$N$5481,0)) -> ADITIVO DE RADIADOR | C31: =INDEX(Base_Gestran!$C$2:$C$5481,MATCH(LARGE(Base_Gestran!$N$2:$N$5481,17),Base_Gestran!$N$2:$N$5481,0)) -> ALMOXARIFADO 1- MANUTENCAO TRANSPORTE | D31: =INDEX(Base_Gestran!$E$2:$E$5481,MATCH(LARGE(Base_Gestran!$N$2:$N$5481,17),Base_Gestran!$N$2:$N$5481,0)) -> 1240 | E31: =INDEX(Base_Gestran!$J$2:$J$5481,MATCH(LARGE(Base_Gestran!$N$2:$N$5481,17),Base_Gestran!$N$2:$N$5481,0)) -> 19616.8
A32: 18 | B32: =INDEX(Base_Gestran!$A$2:$A$5481,MATCH(LARGE(Base_Gestran!$N$2:$N$5481,18),Base_Gestran!$N$2:$N$5481,0)) -> ANEL CAMBIO FSO 4505A (ACCELO 1016) | C32: =INDEX(Base_Gestran!$C$2:$C$5481,MATCH(LARGE(Base_Gestran!$N$2:$N$5481,18),Base_Gestran!$N$2:$N$5481,0)) -> ALMOXARIFADO | D32: =INDEX(Base_Gestran!$E$2:$E$5481,MATCH(LARGE(Base_Gestran!$N$2:$N$5481,18),Base_Gestran!$N$2:$N$5481,0)) -> 1 | E32: =INDEX(Base_Gestran!$J$2:$J$5481,MATCH(LARGE(Base_Gestran!$N$2:$N$5481,18),Base_Gestran!$N$2:$N$5481,0)) -> 19000
A33: 19 | B33: =INDEX(Base_Gestran!$A$2:$A$5481,MATCH(LARGE(Base_Gestran!$N$2:$N$5481,19),Base_Gestran!$N$2:$N$5481,0)) -> CX CV 25KG TAMPA | C33: =INDEX(Base_Gestran!$C$2:$C$5481,MATCH(LARGE(Base_Gestran!$N$2:$N$5481,19),Base_Gestran!$N$2:$N$5481,0)) -> ALMOXARIFADO 9- LOGÍSTICA | D33: =INDEX(Base_Gestran!$E$2:$E$5481,MATCH(LARGE(Base_Gestran!$N$2:$N$5481,19),Base_Gestran!$N$2:$N$5481,0)) -> 4275 | E33: =INDEX(Base_Gestran!$J$2:$J$5481,MATCH(LARGE(Base_Gestran!$N$2:$N$5481,19),Base_Gestran!$N$2:$N$5481,0)) -> 18596.25
A34: 20 | B34: =INDEX(Base_Gestran!$A$2:$A$5481,MATCH(LARGE(Base_Gestran!$N$2:$N$5481,20),Base_Gestran!$N$2:$N$5481,0)) -> SCS PLAST TR PR LISO 43 x 70 | C34: =INDEX(Base_Gestran!$C$2:$C$5481,MATCH(LARGE(Base_Gestran!$N$2:$N$5481,20),Base_Gestran!$N$2:$N$5481,0)) -> ALMOXARIFADO 7- INDUSTRIA | D34: =INDEX(Base_Gestran!$E$2:$E$5481,MATCH(LARGE(Base_Gestran!$N$2:$N$5481,20),Base_Gestran!$N$2:$N$5481,0)) -> 44.8 | E34: =INDEX(Base_Gestran!$J$2:$J$5481,MATCH(LARGE(Base_Gestran!$N$2:$N$5481,20),Base_Gestran!$N$2:$N$5481,0)) -> 18012.736
A36: Nota: 'Chave Único' na Base_Gestran (coluna N) é só um auxiliar de cálculo para o ranking acima — não é um dado do sistema.
A38: OBSERVAÇÕES IDENTIFICADAS NA CONFERÊNCIA MANUAL DE HOJE

Sheet Historico_Saidas
A1: HISTÓRICO DE SAÍDAS — para calcular consumo médio automaticamente | F1: Semanas cobertas pelo período puxado | G1: =(MAX($C$6:$C$5000)-MIN($C$6:$C$5000))/7 -> 36.341607
A2: Cole aqui o extrato de movimentação de cada item (Data + Quantidade da saída). Pode colar os 3 trimestres, um embaixo do outro — não precisa apagar o anterior, só ir acrescentando linhas novas. | F2: Ex: Jan a Set = 9 meses ≈ 39 semanas. Ajuste aqui se puxar período diferente.
A4: Item (Produto) — mesmo nome usado no Painel | B4: Almoxarifado (Local) | C4: Data da Saída | D4: Quantidade
A5: EXEMPLO: BUZINA BIBI 24V | B5: ALMOXARIFADO | C5: 2026-08-05 | D5: 2
A6: LAMPADA H4 24V PHILLIPS | B6: ALMOXARIFADO | C6: 46029.394 | D6: 1
A7: LAMPADA H4 24V PHILLIPS | B7: ALMOXARIFADO | C7: 46029.395 | D7: 1
A8: LAMPADA R5 24V MARCA PHILLIPS | B8: ALMOXARIFADO | C8: 46029.395 | D8: 1
A9: FAROL DE MILHA - LED (REDONDO) | B9: ALMOXARIFADO | C9: 46029.4 | D9: 1
A10: BOTÃO TIC TAC | B10: ALMOXARIFADO | C10: 46029.4 | D10: 1
A11: LAMPADA R5 24V MARCA PHILLIPS | B11: ALMOXARIFADO | C11: 46029.4 | D11: 1
A12: LAMPADA H4 24V PHILLIPS | B12: ALMOXARIFADO | C12: 46029.403 | D12: 1
A13: LAMPADA H7 24V PHILLIPS | B13: ALMOXARIFADO | C13: 46029.404 | D13: 1
A14: LAMPADA 1 POLO 24V | B14: ALMOXARIFADO | C14: 46029.405 | D14: 1
A15: CABO LIGAÇAO FECHADURA ACCELO (LD) (LE) | B15: ALMOXARIFADO | C15: 46029.407 | D15: 1
A16: MACANETA INTERNA ESQUERDA ACCELO / 3233 - A | B16: ALMOXARIFADO | C16: 46029.407 | D16: 1
A17: LAMPADA R5 24V MARCA PHILLIPS | B17: ALMOXARIFADO | C17: 46029.416 | D17: 1
... A1513: COPO DESCARTÁVEL 200ML COPOMAIS | B1513: ALMOXARIFADO 5- LIMPEZA | C1513: 46283.785 | D1513: 4

Sheet Base_Gestran
A1: Produto | B1: Grupo | C1: Almoxarifado | D1: Unidade de Medida | E1: Saldo | F1: Data última entrada | G1: Data última saída | H1: Valor Última Compra | I1: Custo Médio | J1: Valor Total em Estoque | K1: Mínimo (sistema) | L1: Máximo (sistema) | M1: Qtd Cadastros Mesmo Produto | N1: Chave Único (p/ ranking)
A2: ÓLEO SAE 15W 40 20L | B2: MANUTENCAO TRANSPORTE | C2: ALMOXARIFADO 2- MANUTENCAO PREDIAL | D2: Un | E2: 3 | F2: 45803.442 | G2: 45819.462 | H2: 3176.56 | I2: 692.96364 | J2: 2078.88 | K2: 0 | L2: 0 | M2: =COUNTIF($A$2:$A$5481,A2) -> 2 | N2: =J2+ROW()/10000000 -> 2078.88
A3: ÓLEO SAE 15W 40 20L | B3: MANUTENCAO TRANSPORTE | C3: ALMOXARIFADO 1- MANUTENCAO TRANSPORTE | D3: Un | E3: 9 | F3: 46111.794 | H3: 1798 | I3: 696.24889 | J3: 6266.25 | K3: 0 | L3: 0 | M3: =COUNTIF($A$2:$A$5481,A3) -> 2 | N3: =J3+ROW()/10000000 -> 6266.25
A4: ÓLEO BATF TA OH50 | B4: MANUTENCAO TRANSPORTE | C4: ALMOXARIFADO 1- MANUTENCAO TRANSPORTE | D4: Un | E4: 7 | F4: 45805.481 | H4: 614 | I4: 565.14286 | J4: 3955.98 | K4: 0 | L4: 0 | M4: =COUNTIF($A$2:$A$5481,A4) -> 2 | N4: =J4+ROW()/10000000 -> 3955.98
A5: ÓLEO BATF TA OH50 | B5: MANUTENCAO TRANSPORTE | C5: ALMOXARIFADO | D5: Un | E5: 3 | F5: 46007.569 | H5: 593 | I5: 669.06667 | J5: 2007.21 | K5: 0 | L5: 0 | M5: =COUNTIF($A$2:$A$5481,A5) -> 2 | N5: =J5+ROW()/10000000 -> 2007.21
A6: ÓLEO 4L (COD. 3E9902.000) | B6: MANUTENCAO TRANSPORTE | C6: ALMOXARIFADO 1- MANUTENCAO TRANSPORTE | D6: Un | E6: 1 | F6: 45329.451 | H6: 86.1 | I6: 86.1 | J6: 86.1 | K6: 0 | L6: 0 | M6: =COUNTIF($A$2:$A$5481,A6) -> 1 | N6: =J6+ROW()/10000000 -> 86.100001
A7: ÓCULOS ESCURO | B7: ALMOXARIFADO | C7: ALMOXARIFADO | D7: Un | E7: 52 | F7: 45758.448 | G7: 45847.415 | H7: 192 | I7: 4.86333 | J7: 252.72 | K7: 0 | L7: 0 | M7: =COUNTIF($A$2:$A$5481,A7) -> 1 | N7: =J7+ROW()/10000000 -> 252.72
A8: ÁLCOOL IODADO 1L | B8: ALMOXARIFADO | C8: ALMOXARIFADO | D8: Un | E8: 0 | F8: 45338.593 | G8: 46252.461 | H8: 15.98 | I8: 7.99 | J8: 0 | K8: 0 | L8: 0 | M8: =COUNTIF($A$2:$A$5481,A8) -> 1 | N8: =J8+ROW()/10000000 -> 8e-07
A9: ÁLCOOL GEL ALL CLEAN 70% 5L MARCA MERCOTECH | B9: MATERIAL DE LIMPEZA | C9: ALMOXARIFADO 5- LIMPEZA | D9: Un | E9: 15 | F9: 45418.444 | G9: 45474.836 | H9: 776 | I9: 93.5 | J9: 1402.5 | K9: 0 | L9: 0 | M9: =COUNTIF($A$2:$A$5481,A9) -> 1 | N9: =J9+ROW()/10000000 -> 1402.5
A10: ÁLCOOL 70% 50ML | B10: ALMOXARIFADO | C10: ALMOXARIFADO | D10: Un | E10: 0 | F10: 46120.358 | G10: 46252.461 | H10: 3.59 | I10: 3.53 | J10: 0 | K10: 0 | L10: 0 | M10: =COUNTIF($A$2:$A$5481,A10) -> 1 | N10: =J10+ROW()/10000000 -> 1e-06
A11: ÁLCOOL 70% 1 LITRO | B11: MATERIAL DE LIMPEZA | C11: ALMOXARIFADO 9- LOGÍSTICA | D11: Un | E11: 24 | F11: 45762.358 | H11: 173.76 | I11: 7.24 | J11: 173.76 | K11: 0 | L11: 0 | M11: =COUNTIF($A$2:$A$5481,A11) -> 4 | N11: =J11+ROW()/10000000 -> 173.76
A12: ÁLCOOL 70% 1 LITRO | B12: MATERIAL DE LIMPEZA | C12: ALMOXARIFADO | D12: Un | E12: 0 | F12: 45901.764 | G12: 46252.461 | H12: 102 | I12: 8.5051858 | J12: 0 | K12: 0 | L12: 0 | M12: =COUNTIF($A$2:$A$5481,A12) -> 4 | N12: =J12+ROW()/10000000 -> 1.2e-06
A13: ÁLCOOL 70% 1 LITRO | B13: MATERIAL DE LIMPEZA | C13: ALMOXARIFADO 5- LIMPEZA | D13: Un | E13: 220 | F13: 46161.435 | G13: 46279.666 | H13: 249.6 | I13: 8.4250144 | J13: 1854.6 | K13: 0 | L13: 0 | M13: =COUNTIF($A$2:$A$5481,A13) -> 4 | N13: =J13+ROW()/10000000 -> 1854.6
A14: ÁLCOOL 70% 1 LITRO | B14: MATERIAL DE LIMPEZA | C14: ALMOXARIFADO 0- GERAL | D14: Un | E14: 90 | F14: 46251.537 | G14: 46266.353 | H14: 352.8 | I14: 7.35 | J14: 661.5 | K14: 0 | L14: 0 | M14: =COUNTIF($A$2:$A$5481,A14) -> 4 | N14: =J14+ROW()/10000000 -> 661.5
A15: ÁGUA OXIGENADA 10V 100ML | B15: ALMOXARIFADO | C15: ALMOXARIFADO | D15: Un | E15: 5 | F15: 46120.358 | H15: 3.59 | I15: 3.314 | J15: 16.55 | K15: 0 | L15: 0 | M15: =COUNTIF($A$2:$A$5481,A15) -> 1 | N15: =J15+ROW()/10000000 -> 16.550002
A16: ZU- 80 GL 000510 | B16: MANUTENÇAO PREDIAL | C16: ALMOXARIFADO | D16: Un | E16: 2 | F16: 45937.546 | H16: 481.9 | I16: 481.9 | J16: 963.8 | K16: 0 | L16: 0 | M16: =COUNTIF($A$2:$A$5481,A16) -> 1 | N16: =J16+ROW()/10000000 -> 963.8
A17: ZENNITH - ACIDO P/LIMPEZA 1L | B17: MANUTENCAO TRANSPORTE | C17: ALMOXARIFADO | D17: Un | E17: 22 | F17: 46057.586 | G17: 46195.675 | H17: 92 | I17: 23.124348 | J17: 508.64 | K17: 0 | L17: 0 | M17: =COUNTIF($A$2:$A$5481,A17) -> 1 | N17: =J17+ROW()/10000000 -> 508.64
A18: XADREX CORANTE EM PO 250G PRETO | B18: MANUTENÇAO PREDIAL | C18: ALMOXARIFADO | D18: Pç | E18: 1 | F18: 45327.412 | H18: 15.27 | I18: 15.27 | J18: 15.27 | K18: 0 | L18: 0 | M18: =COUNTIF($A$2:$A$5481,A18) -> 1 | N18: =J18+ROW()/10000000 -> 15.270002
A19: WORKER MAÇARICO PORTATIL AUTOMATICO 360º MAPP | B19: ALMOXARIFADO | C19: ALMOXARIFADO | D19: Un | E19: 1 | F19: 46198.644 | H19: 386.94 | I19: 386.94 | J19: 386.94 | K19: 0 | L19: 0 | M19: =COUNTIF($A$2:$A$5481,A19) -> 1 | N19: =J19+ROW()/10000000 -> 386.94
A20: WEG TOMADA SOB 2PT 32A 380V 9H IP44 | B20: MANUTENÇAO PREDIAL | C20: ALMOXARIFADO | D20: Un | E20: 2 | F20: 45749.831 | H20: 212.6 | I20: 106.3 | J20: 212.6 | K20: 0 | L20: 0 | M20: =COUNTIF($A$2:$A$5481,A20) -> 1 | N20: =J20+ROW()/10000000 -> 212.6
A21: WEG PLUG 2PT 32A 380V IP44 | B21: MANUTENÇAO PREDIAL | C21: ALMOXARIFADO | D21: Un | E21: 2 | F21: 45749.831 | H21: 89.2 | I21: 44.6 | J21: 89.2 | K21: 0 | L21: 0 | M21: =COUNTIF($A$2:$A$5481,A21) -> 1 | N21: =J21+ROW()/10000000 -> 89.200002
A22: WEG INT DISJUNTOR 63A | B22: ALMOXARIFADO | C22: ALMOXARIFADO | D22: Un | E22: 1 | F22: 45608.361 | H22: 224.9 | I22: 224.9 | J22: 224.9 | K22: 0 | L22: 0 | M22: =COUNTIF($A$2:$A$5481,A22) -> 1 | N22: =J22+ROW()/10000000 -> 224.9
A23: WEG DISJUNTOR DIN 3 X 50A C | B23: ALMOXARIFADO | C23: ALMOXARIFADO | D23: Un | E23: 5 | F23: 45496.358 | H23: 327.5 | I23: 65.5 | J23: 327.5 | K23: 0 | L23: 0 | M23: =COUNTIF($A$2:$A$5481,A23) -> 1 | N23: =J23+ROW()/10000000 -> 327.5
A24: WEG DISJUNTOR DIN 3 X 25A C | B24: ALMOXARIFADO | C24: ALMOXARIFADO | D24: Un | E24: 1 | F24: 45496.358 | H24: 65.5 | I24: 65.5 | J24: 65.5 | K24: 0 | L24: 0 | M24: =COUNTIF($A$2:$A$5481,A24) -> 1 | N24: =J24+ROW()/10000000 -> 65.500002
A25: WEG CHAVE MAGNETICA PDW 220 3F 3CV | B25: MANUTENÇAO PREDIAL | C25: ALMOXARIFADO | D25: Un | E25: 3 | F25: 45695.377 | H25: 972 | I25: 324 | J25: 972 | K25: 0 | L25: 0 | M25: =COUNTIF($A$2:$A$5481,A25) -> 1 | N25: =J25+ROW()/10000000 -> 972
A26: VÁLVULA P/ MICTÓRIO AUTOMATICO 1/2 | B26: MANUTENÇAO PREDIAL | C26: ALMOXARIFADO 2- MANUTENCAO PREDIAL | D26: Un | E26: 1 | F26: 45300.484 | H26: 131.65 | I26: 131.65 | J26: 131.65 | K26: 0 | L26: 0 | M26: =COUNTIF($A$2:$A$5481,A26) -> 2 | N26: =J26+ROW()/10000000 -> 131.65
A27: VÁLVULA P/ MICTÓRIO AUTOMATICO 1/2 | B27: MANUTENÇAO PREDIAL | C27: ALMOXARIFADO | D27: Un | E27: 8 | F27: 46044.363 | H27: 390 | I27: 174.72 | J27: 1397.76 | K27: 0 | L27: 0 | M27: =COUNTIF($A$2:$A$5481,A27) -> 2 | N27: =J27+ROW()/10000000 -> 1397.76
A28: VONDER ESPIGAO 1/4 MX 1/4 5114 | B28: MANUTENCAO TRANSPORTE | C28: ALMOXARIFADO | D28: Un | E28: 2 | F28: 46251.73 | H28: 10.38 | I28: 5.19 | J28: 10.38 | K28: 0 | L28: 0 | M28: =COUNTIF($A$2:$A$5481,A28) -> 1 | N28: =J28+ROW()/10000000 -> 10.380003
A29: VIRABREQUIM DO MOTOR VW | B29: MANUTENCAO TRANSPORTE | C29: ALMOXARIFADO 1- MANUTENCAO TRANSPORTE | D29: Un | E29: 1 | F29: 45581.544 | G29: 45586.853 | H29: 5380 | I29: 5390 | J29: 5390 | K29: 0 | L29: 0 | M29: =COUNTIF($A$2:$A$5481,A29) -> 1 | N29: =J29+ROW()/10000000 -> 5390
A30: VIRA MACHO ROCAST T LONGO 5M-12M | B30: MANUTENCAO TRANSPORTE | C30: ALMOXARIFADO | D30: Un | E30: 1 | F30: 45364.676 | H30: 169.4 | I30: 169.4 | J30: 169.4 | K30: 0 | L30: 0 | M30: =COUNTIF($A$2:$A$5481,A30) -> 1 | N30: =J30+ROW()/10000000 -> 169.4
A31: VIPES.AUT.FINA ABRAC INOX 13X19MM | B31: MANUTENCAO TRANSPORTE | C31: ALMOXARIFADO | D31: Un | E31: 15 | F31: 46216.603 | H31: 48.75 | I31: 3.25 | J31: 48.75 | K31: 0 | L31: 0 | M31: =COUNTIF($A$2:$A$5481,A31) -> 1 | N31: =J31+ROW()/10000000 -> 48.750003
A32: VIPES ULTRACLEANER 500ML | B32: MANUTENCAO TRANSPORTE | C32: ALMOXARIFADO | D32: Un | E32: 23 | F32: 46216.603 | G32: 46274.572 | H32: 690.48 | I32: 28.77 | J32: 661.71 | K32: 0 | L32: 0 | M32: =COUNTIF($A$2:$A$5481,A32) -> 1 | N32: =J32+ROW()/10000000 -> 661.71
A33: VIPES TINTA SPRAY PRETO FOSCO 400ML | B33: MANUTENCAO TRANSPORTE | C33: ALMOXARIFADO | D33: Un | E33: 24 | F33: 46216.603 | H33: 1319.52 | I33: 54.98 | J33: 1319.52 | K33: 0 | L33: 0 | M33: =COUNTIF($A$2:$A$5481,A33) -> 1 | N33: =J33+ROW()/10000000 -> 1319.52
A34: VIPES SILICONE SPRAY CARRO NOVO | B34: MANUTENCAO TRANSPORTE | C34: ALMOXARIFADO | D34: Un | E34: 24 | F34: 46216.603 | H34: 645.6 | I34: 26.9 | J34: 645.6 | K34: 0 | L34: 0 | M34: =COUNTIF($A$2:$A$5481,A34) -> 1 | N34: =J34+ROW()/10000000 -> 645.6
A35: VINCISOLV P/ACRILICO E DUPLA AÇAO LATA 5 LITROS | B35: ALMOXARIFADO | C35: ALMOXARIFADO | D35: Un | E35: 1 | F35: 45877.684 | H35: 176 | I35: 176 | J35: 176 | K35: 0 | L35: 0 | M35: =COUNTIF($A$2:$A$5481,A35) -> 1 | N35: =J35+ROW()/10000000 -> 176
A36: VINCA | B36: JARDINAGEM | C36: ALMOXARIFADO | D36: Un | E36: 4 | F36: 46027.671 | H36: 95 | I36: 47.5 | J36: 190 | K36: 0 | L36: 0 | M36: =COUNTIF($A$2:$A$5481,A36) -> 1 | N36: =J36+ROW()/10000000 -> 190
A37: VINAGRE PEIXE DE ARROZ | B37: COZINHA | C37: ALMOXARIFADO | D37: Un | E37: 0 | F37: 45888.579 | G37: 46252.486 | H37: 44.94 | I37: 7.49 | J37: 0 | K37: 0 | L37: 0 | M37: =COUNTIF($A$2:$A$5481,A37) -> 1 | N37: =J37+ROW()/10000000 -> 3.7e-06
A38: VIDRO ESPELHO RETROVISOR SUPERIOR LE 23B857521A | B38: MANUTENCAO TRANSPORTE | C38: ALMOXARIFADO | D38: Pç | E38: 1 | F38: 46036.59 | G38: 46078.726 | H38: 254 | I38: 123.5 | J38: 123.5 | K38: 0 | L38: 0 | M38: =COUNTIF($A$2:$A$5481,A38) -> 2 | N38: =J38+ROW()/10000000 -> 123.5
A39: VIDRO ESPELHO RETROVISOR SUPERIOR LE 23B857521A | B39: MANUTENCAO TRANSPORTE | C39: ALMOXARIFADO 1- MANUTENCAO TRANSPORTE | D39: Pç | E39: 3 | F39: 46065.338 | G39: 46090.413 | H39: 1480 | I39: 370 | J39: 1110 | K39: 0 | L39: 0 | M39: =COUNTIF($A$2:$A$5481,A39) -> 2 | N39: =J39+ROW()/10000000 -> 1110
A40: VIDRO ESPELHO RETROVISOR LE 23B857521B | B40: MANUTENCAO TRANSPORTE | C40: ALMOXARIFADO | D40: Pç | E40: 0 | F40: 45737.427 | G40: 46058.728 | H40: 165 | I40: 165 | J40: 0 | K40: 0 | L40: 0 | M40: =COUNTIF($A$2:$A$5481,A40) -> 2 | N40: =J40+ROW()/10000000 -> 4e-06
A41: VIDRO ESPELHO RETROVISOR LE 23B857521B | B41: MANUTENCAO TRANSPORTE | C41: ALMOXARIFADO 1- MANUTENCAO TRANSPORTE | D41: Pç | E41: 3 | F41: 46065.338 | G41: 46120.57 | H41: 580 | I41: 145 | J41: 435 | K41: 0 | L41: 0 | M41: =COUNTIF($A$2:$A$5481,A41) -> 2 | N41: =J41+ROW()/10000000 -> 435
A42: VIDRO ESPELHO RETROVISOR LD 23B877522B | B42: MANUTENCAO TRANSPORTE | C42: ALMOXARIFADO | D42: Pç | E42: 2 | F42: 46059.466 | H42: 127 | I42: 146 | J42: 292 | K42: 0 | L42: 0 | M42: =COUNTIF($A$2:$A$5481,A42) -> 2 | N42: =J42+ROW()/10000000 -> 292
A43: VIDRO ESPELHO RETROVISOR LD 23B877522B | B43: MANUTENCAO TRANSPORTE | C43: ALMOXARIFADO 1- MANUTENCAO TRANSPORTE | D43: Pç | E43: 4 | F43: 46065.338 | H43: 580 | I43: 145 | J43: 580 | K43: 0 | L43: 0 | M43: =COUNTIF($A$2:$A$5481,A43) -> 2 | N43: =J43+ROW()/10000000 -> 580
A44: VIDRO ESPELHO RETROVISOR (LE) MARCA ORIGINAL (VW 11.180) | B44: MANUTENCAO TRANSPORTE | C44: ALMOXARIFADO 1- MANUTENCAO TRANSPORTE | D44: Un | E44: 0 | F44: 45272.876 | G44: 45638.454 | H44: 660 | I44: 330 | J44: 0 | K44: 2 | L44: 6 | M44: =COUNTIF($A$2:$A$5481,A44) -> 1 | N44: =J44+ROW()/10000000 -> 4.4e-06
A45: VIDRO ESPELHO RETROVISOR MARCA ORIGINAL (VW 11.180) | B45: MANUTENCAO TRANSPORTE | C45: ALMOXARIFADO 1- MANUTENCAO TRANSPORTE | D45: Un | E45: 0 | F45: 45272.881 | G45: 45566.422 | H45: 330 | I45: 330 | J45: 0 | K45: 0 | L45: 0 | M45: =COUNTIF($A$2:$A$5481,A45) -> 2 | N45: =J45+ROW()/10000000 -> 4.5e-06
A46: VIDRO ESPELHO RETROVISOR MARCA ORIGINAL (VW 11.180) | B46: MANUTENCAO TRANSPORTE | C46: ALMOXARIFADO | D46: Un | E46: 2 | F46: 45784.396 | H46: 196 | I46: 98 | J46: 196 | K46: 0 | L46: 0 | M46: =COUNTIF($A$2:$A$5481,A46) -> 2 | N46: =J46+ROW()/10000000 -> 196
A47: VIDRO ESPELHO 23B/857522-A | B47: MANUTENCAO TRANSPORTE | C47: ALMOXARIFADO | D47: Un | E47: 1 | F47: 45737.427 | H47: 155 | I47: 155 | J47: 155 | K47: 0 | L47: 0 | M47: =COUNTIF($A$2:$A$5481,A47) -> 2 | N47: =J47+ROW()/10000000 -> 155
A48: VIDRO ESPELHO 23B/857522-A | B48: MANUTENCAO TRANSPORTE | C48: ALMOXARIFADO 1- MANUTENCAO TRANSPORTE | D48: Un | E48: 2 | F48: 46065.338 | G48: 46132.435 | H48: 600 | I48: 150 | J48: 300 | K48: 0 | L48: 0 | M48: =COUNTIF($A$2:$A$5481,A48) -> 2 | N48: =J48+ROW()/10000000 -> 300
A49: VIBRA STOP MINI 1/2 CONJ 4 UND (PÉ) | B49: MANUTENÇAO PREDIAL | C49: ALMOXARIFADO | D49: Un | E49: 1 | F49: 45391.861 | H49: 59.9 | I49: 59.9 | J49: 59.9 | K49: 0 | L49: 0 | M49: =COUNTIF($A$2:$A$5481,A49) -> 1 | N49: =J49+ROW()/10000000 -> 59.900005
A50: VIBRA STOP MICRO III 5/16 | B50: MANUTENÇAO PREDIAL | C50: ALMOXARIFADO | D50: Un | E50: 17 | F50: 46234.595 | G50: 45345.399 | H50: 355.1 | I50: 34.417647 | J50: 585.14 | K50: 0 | L50: 0 | M50: =COUNTIF($A$2:$A$5481,A50) -> 1 | N50: =J50+ROW()/10000000 -> 585.14
A51: VIBRA STOP MICRO III 1/2 | B51: ALMOXARIFADO | C51: ALMOXARIFADO | D51: Un | E51: 6 | F51: 45945.346 | H51: 260.1 | I51: 43.35 | J51: 260.1 | K51: 0 | L51: 0 | M51: =COUNTIF($A$2:$A$5481,A51) -> 1 | N51: =J51+ROW()/10000000 -> 260.10001
A52: VIAPOL VIAFLEX VEDA FITA 30 X 1M ALUMINIO | B52: MANUTENÇAO PREDIAL | C52: ALMOXARIFADO | D52: Un | E52: 0 | F52: 45477.371 | G52: 45477.395 | H52: 369 | I52: 12.3 | J52: 0 | K52: 0 | L52: 0 | M52: =COUNTIF($A$2:$A$5481,A52) -> 1 | N52: =J52+ROW()/10000000 -> 5.2e-06
A53: VIAPOL FITA ADESIVA 45CM | B53: MANUTENÇAO PREDIAL | C53: ALMOXARIFADO | D53: Un | E53: 2 | F53: 46048.582 | H53: 202.77 | I53: 207.525 | J53: 415.06 | K53: 0 | L53: 0 | M53: =COUNTIF($A$2:$A$5481,A53) -> 1 | N53: =J53+ROW()/10000000 -> 415.06001
A54: VERNIZ ZU 80GL | B54: ALMOXARIFADO | C54: ALMOXARIFADO | D54: Un | E54: 1 | F54: 45979.629 | H54: 481.9 | I54: 481.9 | J54: 481.9 | K54: 0 | L54: 0 | M54: =COUNTIF($A$2:$A$5481,A54) -> 1 | N54: =J54+ROW()/10000000 -> 481.90001
A55: VERNIZ PREMIUM SOLARE FILTRO SOLAR MONTANA | B55: MANUTENÇAO PREDIAL | C55: ALMOXARIFADO | D55: Un | E55: 2 | F55: 46048.582 | H55: 169.9 | I55: 112.895 | J55: 225.8 | K55: 0 | L55: 0 | M55: =COUNTIF($A$2:$A$5481,A55) -> 1 | N55: =J55+ROW()/10000000 -> 225.80001
A56: VERNIZ OSMOTOL DECK SEMI BRILHO IPE 3,6L MONTANA | B56: MANUTENÇAO PREDIAL | C56: ALMOXARIFADO | D56: Un | E56: 1 | F56: 46079.574 | H56: 429.9 | I56: 429.9 | J56: 429.9 | K56: 0 | L56: 0 | M56: =COUNTIF($A$2:$A$5481,A56) -> 1 | N56: =J56+ROW()/10000000 -> 429.90001
A57: VERNIZ BI 10.000 C/CATALIZADOR RAPIDO SKY | B57: MANUTENCAO TRANSPORTE | C57: ALMOXARIFADO | D57: Un | E57: 20 | F57: 46157.537 | H57: 319.5 | I57: 57.15 | J57: 1143 | K57: 0 | L57: 0 | M57: =COUNTIF($A$2:$A$5481,A57) -> 1 | N57: =J57+ROW()/10000000 -> 1143
A58: VERGALHAO CA 60 4.20MM (3/16) | B58: MANUTENCAO TRANSPORTE | C58: ALMOXARIFADO | D58: Un | E58: 3 | F58: 45916.586 | H58: 30.66 | I58: 10.22 | J58: 30.66 | K58: 0 | L58: 0 | M58: =COUNTIF($A$2:$A$5481,A58) -> 1 | N58: =J58+ROW()/10000000 -> 30.660006
A59: VERGALHAO CA 50 12.50MM(1/2) | B59: ALMOXARIFADO | C59: ALMOXARIFADO | D59: Un | E59: 4 | F59: 45707.852 | H59: 357.52 | I59: 89.38 | J59: 357.52 | K59: 0 | L59: 0 | M59: =COUNTIF($A$2:$A$5481,A59) -> 1 | N59: =J59+ROW()/10000000 -> 357.52001
A60: VERGALHAO CA 50 10.00 MM | B60: ALMOXARIFADO | C60: ALMOXARIFADO | D60: Un | E60: 4 | F60: 45482.421 | H60: 225.64 | I60: 56.41 | J60: 225.64 | K60: 0 | L60: 0 | M60: =COUNTIF($A$2:$A$5481,A60) -> 1 | N60: =J60+ROW()/10000000 -> 225.64001
A61: VENTOSA SIMPLES P/REM DE VIDRO | B61: MANUTENÇAO PREDIAL | C61: ALMOXARIFADO | D61: Un | E61: 1 | F61: 45439.818 | H61: 82.9 | I61: 82.9 | J61: 82.9 | K61: 0 | L61: 0 | M61: =COUNTIF($A$2:$A$5481,A61) -> 1 | N61: =J61+ROW()/10000000 -> 82.900006
A62: VENTILADOR DE PAREDE VENTISOL OSCILANTE PREMIUM BIVOLT | B62: PATRIMÔNIO | C62: ALMOXARIFADO | D62: Un | E62: 0 | F62: 45333.548 | G62: 46252.61 | H62: 564.46 | I62: 282.23 | J62: 0 | K62: 0 | L62: 0 | M62: =COUNTIF($A$2:$A$5481,A62) -> 1 | N62: =J62+ROW()/10000000 -> 6.2e-06
A63: VENTILADOR DE COLUNA BRITANIA BVT 350 MAXX FORCE | B63: MANUTENCAO TRANSPORTE | C63: ALMOXARIFADO | D63: Un | E63: 0 | F63: 45470.386 | G63: 46252.61 | H63: 174.03 | I63: 174.03 | J63: 0 | K63: 0 | L63: 0 | M63: =COUNTIF($A$2:$A$5481,A63) -> 1 | N63: =J63+ROW()/10000000 -> 6.3e-06
A64: VENTILADOR (COD. VO221666250) | B64: MANUTENCAO TRANSPORTE | C64: ALMOXARIFADO 1- MANUTENCAO TRANSPORTE | D64: Un | E64: 0 | F64: 45303.397 | G64: 45352.445 | H64: 5754.59 | I64: 5754.59 | J64: 0 | K64: 0 | L64: 0 | M64: =COUNTIF($A$2:$A$5481,A64) -> 1 | N64: =J64+ROW()/10000000 -> 6.4e-06
A65: VELA TREZE ESTRELAS OURO 4C | B65: ALMOXARIFADO | C65: ALMOXARIFADO 0- GERAL | D65: Un | E65: 1 | F65: 45342.823 | H65: 6.39 | I65: 6.39 | J65: 6.39 | K65: 0 | L65: 0 | M65: =COUNTIF($A$2:$A$5481,A65) -> 1 | N65: =J65+ROW()/10000000 -> 6.3900065
A66: VELA TITAN / FAN 150 /BROS NGK | B66: MANUTENCAO TRANSPORTE | C66: ALMOXARIFADO | D66: Un | E66: 2 | F66: 46171.653 | H66: 59.8 | I66: 29.9 | J66: 59.8 | K66: 0 | L66: 0 | M66: =COUNTIF($A$2:$A$5481,A66) -> 1 | N66: =J66+ROW()/10000000 -> 59.800007
A67: VELA NGK BP5HS VW SEDAN(BUGRE) | B67: MANUTENCAO TRANSPORTE | C67: ALMOXARIFADO | D67: Un | E67: 1 | F67: 45407.739 | H67: 65 | I67: 65 | J67: 65 | K67: 0 | L67: 0 | M67: =COUNTIF($A$2:$A$5481,A67) -> 1 | N67: =J67+ROW()/10000000 -> 65.000007
A68: VELA IGUINIÇÃO BKR7ESBD FOX FLEX 04 MARCA PARALELA SAVEIRO | B68: MANUTENCAO TRANSPORTE | C68: ALMOXARIFADO 1- MANUTENCAO TRANSPORTE | D68: Un | E68: 3 | F68: 45590.438 | G68: 45594.448 | H68: 102 | I68: 25.5 | J68: 76.5 | K68: 0 | L68: 0 | M68: =COUNTIF($A$2:$A$5481,A68) -> 1 | N68: =J68+ROW()/10000000 -> 76.500007
A69: VELA DR8EA-N FAZER/ LANDER 2012 E. | B69: MANUTENCAO TRANSPORTE | C69: ALMOXARIFADO | D69: Un | E69: 1 | F69: 46171.653 | H69: 24.5 | I69: 24.5 | J69: 24.5 | K69: 0 | L69: 0 | M69: =COUNTIF($A$2:$A$5481,A69) -> 1 | N69: =J69+ROW()/10000000 -> 24.500007
A70: VELA DE IGNIÇÃO NGK BPM7A (ROÇADEIRA) | B70: JARDINAGEM | C70: ALMOXARIFADO 6- JARDINAGEM | D70: Un | E70: 1 | F70: 45282.409 | H70: 25 | I70: 25 | J70: 25 | K70: 0 | L70: 0 | M70: =COUNTIF($A$2:$A$5481,A70) -> 2 | N70: =J70+ROW()/10000000 -> 25.000007
A71: VELA DE IGNIÇÃO NGK BPM7A (ROÇADEIRA) | B71: JARDINAGEM | C71: ALMOXARIFADO | D71: Un | E71: 5 | F71: 46001.558 | H71: 29 | I71: 27.6 | J71: 138 | K71: 0 | L71: 0 | M71: =COUNTIF($A$2:$A$5481,A71) -> 2 | N71: =J71+ROW()/10000000 -> 138.00001
A72: VELA AQUECEDORA SPRINTER | B72: MANUTENCAO TRANSPORTE | C72: ALMOXARIFADO | D72: Un | E72: 0 | F72: 45546.833 | G72: 45546.835 | H72: 400 | I72: 100 | J72: 0 | K72: 0 | L72: 0 | M72: =COUNTIF($A$2:$A$5481,A72) -> 1 | N72: =J72+ROW()/10000000 -> 7.2e-06
A73: VEDAÇÃO (COD. 5256541) | B73: MANUTENCAO TRANSPORTE | C73: ALMOXARIFADO 1- MANUTENCAO TRANSPORTE | D73: Un | E73: 1 | F73: 45581.544 | G73: 45586.853 | H73: 355 | I73: 355 | J73: 355 | K73: 0 | L73: 0 | M73: =COUNTIF($A$2:$A$5481,A73) -> 1 | N73: =J73+ROW()/10000000 -> 355.00001
A74: VEDAÇAO P/REPARO MANGUEIRA DE MANOMETRO(MANIFOLD) | B74: MANUTENCAO TRANSPORTE | C74: ALMOXARIFADO | D74: Un | E74: 11 | F74: 45915.702 | H74: 60 | I74: 18.181818 | J74: 199.98 | K74: 0 | L74: 0 | M74: =COUNTIF($A$2:$A$5481,A74) -> 1 | N74: =J74+ROW()/10000000 -> 199.98001
A75: VEDAÇAO DA JANELA A9799877151 | B75: MANUTENCAO TRANSPORTE | C75: ALMOXARIFADO 1- MANUTENCAO TRANSPORTE | D75: Un | E75: 0 | F75: 46254.583 | G75: 46266.718 | H75: 410 | I75: 410 | J75: 0 | K75: 0 | L75: 0 | M75: =COUNTIF($A$2:$A$5481,A75) -> 1 | N75: =J75+ROW()/10000000 -> 7.5e-06
A76: VEDA TUDO 100G | B76: ALMOXARIFADO | C76: ALMOXARIFADO | D76: Un | E76: 2 | F76: 45461.825 | H76: 46.4 | I76: 23.2 | J76: 46.4 | K76: 0 | L76: 0 | M76: =COUNTIF($A$2:$A$5481,A76) -> 1 | N76: =J76+ROW()/10000000 -> 46.400008
A77: VEDA PORTA 70CM | B77: MANUTENÇAO PREDIAL | C77: ALMOXARIFADO | D77: Un | E77: 2 | F77: 45561.608 | H77: 19.48 | I77: 9.74 | J77: 19.48 | K77: 0 | L77: 0 | M77: =COUNTIF($A$2:$A$5481,A77) -> 1 | N77: =J77+ROW()/10000000 -> 19.480008
A78: VEDA ESCAPE | B78: MANUTENCAO TRANSPORTE | C78: ALMOXARIFADO 1- MANUTENCAO TRANSPORTE | D78: Un | E78: 4 | F78: 45618.404 | H78: 20 | I78: 10 | J78: 40 | K78: 0 | L78: 0 | M78: =COUNTIF($A$2:$A$5481,A78) -> 1 | N78: =J78+ROW()/10000000 -> 40.000008
A79: VASSOURA V16 | B79: MATERIAL DE LIMPEZA | C79: ALMOXARIFADO 5- LIMPEZA | D79: Un | E79: 4 | F79: 45364.839 | H79: 188 | I79: 47 | J79: 188 | K79: 0 | L79: 0 | M79: =COUNTIF($A$2:$A$5481,A79) -> 2 | N79: =J79+ROW()/10000000 -> 188.00001
A80: VASSOURA V16 | B80: MATERIAL DE LIMPEZA | C80: ALMOXARIFADO | D80: Un | E80: 6 | F80: 45491.74 | H80: 87 | I80: 34.975 | J80: 209.88 | K80: 0 | L80: 0 | M80: =COUNTIF($A$2:$A$5481,A80) -> 2 | N80: =J80+ROW()/10000000 -> 209.88001
A81: VASSOURA ROSSI MODERNA | B81: MANUTENÇAO PREDIAL | C81: ALMOXARIFADO | D81: Un | E81: 1 | F81: 46056.367 | H81: 18 | I81: 18 | J81: 18 | K81: 0 | L81: 0 | M81: =COUNTIF($A$2:$A$5481,A81) -> 1 | N81: =J81+ROW()/10000000 -> 18.000008
A82: VASSOURA PARABRISA SEM CABO | B82: ALMOXARIFADO | C82: ALMOXARIFADO | D82: Un | E82: 10 | F82: 45677.375 | H82: 269.9 | I82: 26.99 | J82: 269.9 | K82: 0 | L82: 0 | M82: =COUNTIF($A$2:$A$5481,A82) -> 1 | N82: =J82+ROW()/10000000 -> 269.90001
A83: VASSOURA PALHETA FIXA C/CABO | B83: JARDINAGEM | C83: ALMOXARIFADO | D83: Un | E83: 2 | F83: 46129.544 | H83: 53 | I83: 66.65 | J83: 133.3 | K83: 0 | L83: 0 | M83: =COUNTIF($A$2:$A$5481,A83) -> 1 | N83: =J83+ROW()/10000000 -> 133.30001
A84: VASSOURA MULTIUSO | B84: MATERIAL DE LIMPEZA | C84: ALMOXARIFADO 5- LIMPEZA | D84: Un | E84: 2 | F84: 45446.387 | H84: 33.9 | I84: 16.95 | J84: 33.9 | K84: 0 | L84: 0 | M84: =COUNTIF($A$2:$A$5481,A84) -> 2 | N84: =J84+ROW()/10000000 -> 33.900008
A85: VASSOURA MULTIUSO | B85: MATERIAL DE LIMPEZA | C85: ALMOXARIFADO | D85: Un | E85: 5 | F85: 45600.715 | H85: 47.7 | I85: 15.136 | J85: 75.7 | K85: 0 | L85: 0 | M85: =COUNTIF($A$2:$A$5481,A85) -> 2 | N85: =J85+ROW()/10000000 -> 75.700008
A86: VASSOURA LAVA ONIBUS PITA C/CABO 1,5MTS START | B86: MANUTENCAO TRANSPORTE | C86: ALMOXARIFADO 1- MANUTENCAO TRANSPORTE | D86: Un | E86: 4 | F86: 45919.392 | H86: 164.64 | I86: 41.16 | J86: 164.64 | K86: 0 | L86: 0 | M86: =COUNTIF($A$2:$A$5481,A86) -> 1 | N86: =J86+ROW()/10000000 -> 164.64001
A87: VASSOURA JARDIM PLASTICA 26D C/C LARANJA | B87: MANUTENÇAO PREDIAL | C87: ALMOXARIFADO 2- MANUTENCAO PREDIAL | D87: Un | E87: 1 | F87: 45288.569 | H87: 37.53 | I87: 37.53 | J87: 37.53 | K87: 0 | L87: 5 | M87: =COUNTIF($A$2:$A$5481,A87) -> 1 | N87: =J87+ROW()/10000000 -> 37.530009
... A89: VASSOURA GARI | B89: MANUTENCAO TRANSPORTE | C89: ALMOXARIFADO | D89: Un | E89: 6 | F89: 46017.572 | H89: 179.4 | I89: 29.9 | J89: 179.4 | K89: 0 | L89: 0 | M89: =COUNTIF($A$2:$A$5481,A89) -> 1 | N89: =J89+ROW()/10000000 -> 179.40001
A90: VASSOURA DE PIAÇAVA | B90: MATERIAL DE LIMPEZA | C90: ALMOXARIFADO 5- LIMPEZA | D90: Un | E90: 1 | F90: 45302.818 | G90: 45490.551 | H90: 41.5 | I90: 20.75 | J90: 20.75 | K90: 1 | L90: 10 | M90: =COUNTIF($A$2:$A$5481,A90) -> 2 | N90: =J90+ROW()/10000000 -> 20.750009
A91: VASSOURA DE PIAÇAVA | B91: MATERIAL DE LIMPEZA | C91: ALMOXARIFADO | D91: Un | E91: 54 | F91: 46190.724 | G91: 45862.414 | H91: 117.6 | I91: 22.538142 | J91: 1217.16 | K91: 1 | L91: 10 | M91: =COUNTIF($A$2:$A$5481,A91) -> 2 | N91: =J91+ROW()/10000000 -> 1217.16
A92: VASSOURA DE PELO ANIMAL 40 | B92: MATERIAL DE LIMPEZA | C92: ALMOXARIFADO 5- LIMPEZA | D92: Un | E92: 2 | F92: 45336.588 | H92: 204 | I92: 102 | J92: 204 | K92: 0 | L92: 0 | M92: =COUNTIF($A$2:$A$5481,A92) -> 1 | N92: =J92+ROW()/10000000 -> 204.00001
A93: VASSOURA C/ESCOVA REFORÇADO | B93: MANUTENCAO TRANSPORTE | C93: ALMOXARIFADO | D93: Un | E93: 8 | F93: 46216.603 | H93: 761.52 | I93: 95.19 | J93: 761.52 | K93: 0 | L93: 0 | M93: =COUNTIF($A$2:$A$5481,A93) -> 1 | N93: =J93+ROW()/10000000 -> 761.52001
A94: VASSOURA ANCINHO DE FERRO | B94: JARDINAGEM | C94: ALMOXARIFADO | D94: Un | E94: 1 | F94: 45897.476 | H94: 39.5 | I94: 39.5 | J94: 39.5 | K94: 0 | L94: 0 | M94: =COUNTIF($A$2:$A$5481,A94) -> 1 | N94: =J94+ROW()/10000000 -> 39.500009
A95: VASSOURA ANCINHO | B95: JARDINAGEM | C95: ALMOXARIFADO | D95: Un | E95: 3 | F95: 46156.553 | H95: 54 | I95: 50 | J95: 150 | K95: 0 | L95: 0 | M95: =COUNTIF($A$2:$A$5481,A95) -> 1 | N95: =J95+ROW()/10000000 -> 150.00001
A96: VASOS DE PLANTA DIVERSO | B96: JARDINAGEM | C96: ALMOXARIFADO 6- JARDINAGEM | D96: Un | E96: 0 | F96: 45282.385 | G96: 45320.399 | H96: 16 | I96: 8 | J96: 0 | K96: 0 | L96: 0 | M96: =COUNTIF($A$2:$A$5481,A96) -> 1 | N96: =J96+ROW()/10000000 -> 9.6e-06
A97: VASELINA SPRAY 300ML TEK BOND | B97: ALMOXARIFADO | C97: ALMOXARIFADO | D97: Un | E97: 14 | F97: 46041.568 | H97: 64.16 | I97: 20.848571 | J97: 291.9 | K97: 0 | L97: 0 | M97: =COUNTIF($A$2:$A$5481,A97) -> 1 | N97: =J97+ROW()/10000000 -> 291.90001
A98: VASELINA SOLIDA BALDE | B98: MANUTENCAO TRANSPORTE | C98: ALMOXARIFADO | D98: Un | E98: 3 | F98: 45757.413 | G98: 45427.816 | H98: 141.8 | I98: 91.86667 | J98: 275.61 | K98: 0 | L98: 0 | M98: =COUNTIF($A$2:$A$5481,A98) -> 1 | N98: =J98+ROW()/10000000 -> 275.61001
A99: VASELINA LÍQUIDA 1LT | B99: ALMOXARIFADO | C99: ALMOXARIFADO | D99: Un | E99: 0 | F99: 45344.635 | G99: 46254.357 | H99: 88.44 | I99: 44.22 | J99: 0 | K99: 0 | L99: 0 | M99: =COUNTIF($A$2:$A$5481,A99) -> 2 | N99: =J99+ROW()/10000000 -> 9.9e-06
A100: VASELINA LÍQUIDA 1LT | B100: ALMOXARIFADO | C100: ALMOXARIFADO 1- MANUTENCAO TRANSPORTE | D100: Un | E100: 19 | F100: 46253.343 | G100: 46265.593 | H100: 660 | I100: 33 | J100: 627 | K100: 0 | L100: 0 | M100: =COUNTIF($A$2:$A$5481,A100) -> 2 | N100: =J100+ROW()/10000000 -> 627.00001
A101: VASELINA LIQUIDA 500ML | B101: ALMOXARIFADO | C101: ALMOXARIFADO | D101: Un | E101: 6 | F101: 45888.572 | G101: 45887.368 | H101: 87.87 | I101: 30.29 | J101: 181.74 | K101: 0 | L101: 0 | M101: =COUNTIF($A$2:$A$5481,A101) -> 1 | N101: =J101+ROW()/10000000 -> 181.74001
...

Sheet Historico_Entradas
A1: Data/Hora | B1: Modelo | C1: Número | D1: Emitente | E1: Almoxarifado | F1: Empresa | G1: Produto | H1: Quantidade | I1: Valor Total | J1: Última Alteração | K1: Usuário | L1: Chave (aux)
A2: 46026.365 | B2: Registro de Movimentação de Materiais | C2: 14759 | D2: MASTER LOAD | E2: ALMOXARIFADO 9- LOGÍSTICA | F2: MAYARA COMERCIO DE GENEROS ALIMENTICIOS LTDA | G2: CONJUNTO DE ESCOVA E PARAFUSO - CROWN - PE4500 (125789) | H2: 1 | I2: 650.52 | J2: 46086.372 | K2: CRISTIANO CRISPIM | L2: =IF(G2="","",G2&"|"&TEXT(A2,"0")) -> CONJUNTO DE ESCOVA E PARAFUSO - CROWN - PE4500 (125789)|46026
A3: 46026.365 | B3: Registro de Movimentação de Materiais | C3: 14759 | D3: MASTER LOAD | E3: ALMOXARIFADO 9- LOGÍSTICA | F3: MAYARA COMERCIO DE GENEROS ALIMENTICIOS LTDA | G3: PORTA ESCOVAS - PC4500 (128742) | H3: 1 | I3: 946.5 | J3: 46086.372 | K3: CRISTIANO CRISPIM | L3: =IF(G3="","",G3&"|"&TEXT(A3,"0")) -> PORTA ESCOVAS - PC4500 (128742)|46026
A4: 46026.365 | B4: Registro de Movimentação de Materiais | C4: 14759 | D4: MASTER LOAD | E4: ALMOXARIFADO 9- LOGÍSTICA | F4: MAYARA COMERCIO DE GENEROS ALIMENTICIOS LTDA | G4: ROLAMENTO 6201 (128736) | H4: 1 | I4: 191.16 | J4: 46086.372 | K4: CRISTIANO CRISPIM | L4: =IF(G4="","",G4&"|"&TEXT(A4,"0")) -> ROLAMENTO 6201 (128736)|46026
A5: 46027.541 | B5: Registro de Movimentação de Materiais | C5: 4452 | D5: AUTOPECAS RIO BONITO | E5: ALMOXARIFADO | F5: BOIBOM PRIME DISTRIBUIDORA DE GENEROS ALIMENTICIOS LTDA | G5: ESPELHO RETROVISOR ACCELO | H5: 8 | I5: 1120 | J5: 46027.543 | K5: CRISTIANO CRISPIM | L5: =IF(G5="","",G5&"|"&TEXT(A5,"0")) -> ESPELHO RETROVISOR ACCELO|46028
A6: 46027.549 | B6: Registro de Movimentação de Materiais | C6: 84905 | D6: ENGELUZ | E6: ALMOXARIFADO | F6: BOIBOM PRIME DISTRIBUIDORA DE GENEROS ALIMENTICIOS LTDA | G6: LAMPADA LE TKL 90 15W 6500K | H6: 20 | I6: 318 | J6: 46028.554 | K6: CRISTIANO CRISPIM | L6: =IF(G6="","",G6&"|"&TEXT(A6,"0")) -> LAMPADA LE TKL 90 15W 6500K|46028
A7: 46027.549 | B7: Registro de Movimentação de Materiais | C7: 84905 | D7: ENGELUZ | E7: ALMOXARIFADO | F7: BOIBOM PRIME DISTRIBUIDORA DE GENEROS ALIMENTICIOS LTDA | G7: REFIL GÁS P/MAÇARICO 400G ANDFER | H7: 2 | I7: 61.2 | J7: 46028.554 | K7: CRISTIANO CRISPIM | L7: =IF(G7="","",G7&"|"&TEXT(A7,"0")) -> REFIL GÁS P/MAÇARICO 400G ANDFER|46028
A8: 46027.549 | B8: Registro de Movimentação de Materiais | C8: 84905 | D8: ENGELUZ | E8: ALMOXARIFADO | F8: BOIBOM PRIME DISTRIBUIDORA DE GENEROS ALIMENTICIOS LTDA | G8: GESSO | H8: 2 | I8: 12.9 | J8: 46028.554 | K8: CRISTIANO CRISPIM | L8: =IF(G8="","",G8&"|"&TEXT(A8,"0")) -> GESSO|46028
A9: 46027.549 | B9: Registro de Movimentação de Materiais | C9: 84905 | D9: ENGELUZ | E9: ALMOXARIFADO | F9: BOIBOM PRIME DISTRIBUIDORA DE GENEROS ALIMENTICIOS LTDA | G9: BOCAL CERAMICO P80 | H9: 10 | I9: 48.5 | J9: 46028.554 | K9: CRISTIANO CRISPIM | L9: =IF(G9="","",G9&"|"&TEXT(A9,"0")) -> BOCAL CERAMICO P80|46028
A10: 46027.654 | B10: Registro de Movimentação de Materiais | C10: 213 | D10: MULTIMARCAS PEÇAS | E10: ALMOXARIFADO | F10: BOIBOM PRIME DISTRIBUIDORA DE GENEROS ALIMENTICIOS LTDA | G10: ESPELHO COMPLETO C/BIFOCAL CONVEXO LE P/VW DELIVERY 2018 | H10: 1 | I10: 500 | J10: 46028.672 | K10: CRISTIANO CRISPIM | L10: =IF(G10="","",G10&"|"&TEXT(A10,"0")) -> ESPELHO COMPLETO C/BIFOCAL CONVEXO LE P/VW DELIVERY 2018|46028
A11: 46027.654 | B11: Registro de Movimentação de Materiais | C11: 213 | D11: MULTIMARCAS PEÇAS | E11: ALMOXARIFADO | F11: BOIBOM PRIME DISTRIBUIDORA DE GENEROS ALIMENTICIOS LTDA | G11: ESPELHO COMPLETO C/BIFOCAL CONVEXO LD P/VW DELIVERY 2018 | H11: 1 | I11: 500 | J11: 46028.672 | K11: CRISTIANO CRISPIM | L11: =IF(G11="","",G11&"|"&TEXT(A11,"0")) -> ESPELHO COMPLETO C/BIFOCAL CONVEXO LD P/VW DELIVERY 2018|46028
A12: 46027.671 | B12: Registro de Movimentação de Materiais | C12: 216 | D12: HORTO TROPICAL | E12: ALMOXARIFADO | F12: BOIBOM PRIME DISTRIBUIDORA DE GENEROS ALIMENTICIOS LTDA | G12: COMPOSTO VEGETAL | H12: 2 | I12: 44 | J12: 46027.672 | K12: CRISTIANO CRISPIM | L12: =IF(G12="","",G12&"|"&TEXT(A12,"0")) -> COMPOSTO VEGETAL|46028
A13: 46027.671 | B13: Registro de Movimentação de Materiais | C13: 216 | D13: HORTO TROPICAL | E13: ALMOXARIFADO | F13: BOIBOM PRIME DISTRIBUIDORA DE GENEROS ALIMENTICIOS LTDA | G13: VINCA | H13: 2 | I13: 95 | J13: 46027.672 | K13: CRISTIANO CRISPIM | L13: =IF(G13="","",G13&"|"&TEXT(A13,"0")) -> VINCA|46028
... A2009: 46283.712 | B2009: Registro de Movimentação de Materiais | C2009: 0 | D2009: MAYARA COMERCIO DE GENEROS ALIMENTICIOS LTDA | E2009: ALMOXARIFADO 1- MANUTENCAO TRANSPORTE | F2009: MAYARA COMERCIO DE GENEROS ALIMENTICIOS LTDA | G2009: LAMPADA H4 24V MARCA WURTH | H2009: 1 | I2009: 0.01 | J2009: 46283.713 | K2009: THAYNA OLIVEIRA FIGU | L2009: =IF(G2009="","",G2009&"|"&TEXT(A2009,"0")) -> LAMPADA H4 24V MARCA WURTH|46284

Sheet Historico_Snapshot
A1: HISTÓRICO DIÁRIO — INDICADORES DO ESTOQUE (para o gráfico de tendência) | J1: VALORES AO VIVO — AGORA (copie pra uma linha nova)
A2: Uma linha por MÊS (não por dia). Clicar em 'Salvar snapshot' atualiza a linha do mês atual se já existir; só cria linha nova quando o mês mudar. Valores são fixos (não fórmula) — são a 'foto' daquele mês. | J2: Data de hoje | K2: =TODAY() -> 46288
J3: Valor Total em Estoque | K3: =Analises_Gerais!B9 -> 5119194.7
A4: Data | B4: Valor Total em Estoque | C4: Total Cadastros | D4: Com Saldo | E4: Saldo Zerado | F4: Saldo Negativo | G4: Giro Ativo | H4: Itens Curados | J4: Total Cadastros | K4: =Analises_Gerais!B4 -> 5480
A5: 46286 | B5: 5119194.7 | C5: 5480 | D5: 4484 | E5: 990 | F5: 6 | G5: 668 | H5: 41 | J5: Com Saldo | K5: =Analises_Gerais!B5 -> 4484
J6: Saldo Zerado | K6: =Analises_Gerais!B6 -> 990
J7: Saldo Negativo | K7: =Analises_Gerais!B7 -> 6
J8: Itens Curados | K8: =COUNTIFS(Controle_Estoque!E8:E150,"<>",Controle_Estoque!F8:F150,"<>") -> 41
J10: Obs: Giro Ativo não dá pra calcular ao vivo aqui (depende de somar saídas — pesado pra fórmula). Confira no dashboard e digite na hora de salvar.
A308: COMO FUNCIONA O BOTÃO 'SALVAR SNAPSHOT DE HOJE'
A309: • Hoje (setembro): você clica em "Salvar snapshot de hoje" → ele pega o valor que está na tela agora (ex: R$ 5.119.194,72) e grava uma linha: 21/09/2026 | R$ 5.119.194,72 | ...
A310: • Se você clicar de novo ainda em setembro (ex: quer atualizar depois de corrigir mais itens) → ele não cria uma segunda linha de setembro — encontra que já existe um snapshot desse mês e atualiza essa mesma linha, sem duplicar.
A311: • No mês que vem (outubro): você atualiza o Gestran, sobe os dados, clica em "Salvar snapshot de hoje" de novo → como o mês mudou, ele cria uma linha nova: 05/10/2026 | R$ 4.980.000,00 | ...
A312: • O gráfico então mostra: uma barra por mês, sempre com o último valor salvo naquele mês — o sistema decide sozinho se atualiza a linha do mês atual ou cria uma nova, sem você precisar gerenciar isso manualmente.
